{
    "metadata": {
        "page_hash": "10161f7c986fb2176122bc095fb4034f527ccff1767757dbd570639c02cf9a17",
        "original_filename": "faa-h-8083-21.pdf",
        "page_no": 11,
        "num_pages": 207,
        "original_width": 594,
        "original_height": 774,
        "coco_width": 1025,
        "coco_height": 1025,
        "collection": "faa_regulations",
        "doc_category": "laws_and_regulations"
    },
    "cells": [
        {
            "bbox": [
                909.4288169191918,
                987.1193636950904,
                30.21655134680134,
                10.929360465116282
            ],
            "text": "1-1",
            "font": {
                "color": [
                    0,
                    0,
                    0,
                    255
                ],
                "name": "/Courier",
                "size": 1
            },
            "text_vi": "1-1"
        },
        {
            "bbox": [
                110.43771043771044,
                192.03360432816532,
                397.87007407407407,
                12.514548126615068
            ],
            "text": "Helicopters come in many sizes and shapes, but most",
            "font": {
                "color": [
                    0,
                    0,
                    0,
                    255
                ],
                "name": "/Times-Roman",
                "size": 1
            },
            "text_vi": "Trực thăng có nhiều kích cỡ và hình dạng, nhưng hầu hết"
        },
        {
            "bbox": [
                110.43771043771044,
                207.92564664082693,
                397.57838047138046,
                12.514548126614955
            ],
            "text": "share the same major components. These components",
            "font": {
                "color": [
                    0,
                    0,
                    0,
                    255
                ],
                "name": "/Times-Roman",
                "size": 1
            },
            "text_vi": "Chia sẻ các thành phần chính tương tự. Những thành phần này"
        },
        {
            "bbox": [
                110.43771043771044,
                223.81767571059436,
                198.5898674242424,
                12.51456136950901
            ],
            "text": "include a cabin where the ",
            "font": {
                "color": [
                    0,
                    0,
                    0,
                    255
                ],
                "name": "/Times-Roman",
                "size": 1
            },
            "text_vi": "bao gồm một cabin trong đó "
        },
        {
            "bbox": [
                309.03266835016836,
                223.81655006459948,
                63.41357491582488,
                12.514548126614955
            ],
            "text": "payload",
            "font": {
                "color": [
                    0,
                    0,
                    0,
                    255
                ],
                "name": "/Times-Bold",
                "size": 1
            },
            "text_vi": "Tải trọng"
        },
        {
            "bbox": [
                377.5087079124579,
                223.81655006459948,
                130.7988005050505,
                12.514548126614955
            ],
            "text": "and crew are car-",
            "font": {
                "color": [
                    0,
                    0,
                    0,
                    255
                ],
                "name": "/Times-Roman",
                "size": 1
            },
            "text_vi": "Và phi hành đoàn là xe hơi-"
        },
        {
            "bbox": [
                110.43747403198653,
                239.70859237726108,
                398.21249482323236,
                12.514548126614955
            ],
            "text": "ried; an airframe, which houses the various compo-",
            "font": {
                "color": [
                    0,
                    0,
                    0,
                    255
                ],
                "name": "/Times-Roman",
                "size": 1
            },
            "text_vi": "ried; một khung máy bay, nơi chứa các compo-"
        },
        {
            "bbox": [
                110.43747403198653,
                255.6006214470284,
                397.7341269781145,
                12.51456136950901
            ],
            "text": "nents, or where components are attached; a powerplant",
            "font": {
                "color": [
                    0,
                    0,
                    0,
                    255
                ],
                "name": "/Times-Roman",
                "size": 1
            },
            "text_vi": "Nents, hoặc nơi các thành phần được đính kèm; một động cơ"
        },
        {
            "bbox": [
                110.43747403198653,
                271.49266375969,
                398.0928942340067,
                12.51454812661484
            ],
            "text": "or engine; and a transmission, which, among other",
            "font": {
                "color": [
                    0,
                    0,
                    0,
                    255
                ],
                "name": "/Times-Roman",
                "size": 1
            },
            "text_vi": "hoặc động cơ; và truyền tải, trong số những người khác"
        },
        {
            "bbox": [
                110.43747403198653,
                287.3847060723514,
                397.7341269781145,
                12.514548126615068
            ],
            "text": "things, takes the power from the engine and transmits it",
            "font": {
                "color": [
                    0,
                    0,
                    0,
                    255
                ],
                "name": "/Times-Roman",
                "size": 1
            },
            "text_vi": "mọi thứ, lấy điện từ động cơ và truyền nó"
        },
        {
            "bbox": [
                110.43747403198653,
                303.276748385013,
                398.21249482323236,
                12.514548126614955
            ],
            "text": "to the main rotor, which provides the aerodynamic",
            "font": {
                "color": [
                    0,
                    0,
                    0,
                    255
                ],
                "name": "/Times-Roman",
                "size": 1
            },
            "text_vi": "cho rôto chính, cung cấp tính khí động học"
        },
        {
            "bbox": [
                110.43747403198653,
                319.1687774547804,
                398.2125465909091,
                12.514548126614955
            ],
            "text": "forces that make the helicopter fly. Then, to keep the",
            "font": {
                "color": [
                    0,
                    0,
                    0,
                    255
                ],
                "name": "/Times-Roman",
                "size": 1
            },
            "text_vi": "Các lực lượng làm cho máy bay trực thăng bay. Sau đó, để giữ"
        },
        {
            "bbox": [
                110.43747403198653,
                335.0608197674419,
                233.38678312289562,
                12.514548126614955
            ],
            "text": "helicopter from turning due to ",
            "font": {
                "color": [
                    0,
                    0,
                    0,
                    255
                ],
                "name": "/Times-Roman",
                "size": 1
            },
            "text_vi": "máy bay trực thăng từ rẽ do "
        },
        {
            "bbox": [
                343.8374579124579,
                335.0568601421188,
                52.72537878787875,
                12.514548126615068
            ],
            "text": "torque",
            "font": {
                "color": [
                    0,
                    0,
                    0,
                    255
                ],
                "name": "/Times-Bold",
                "size": 1
            },
            "text_vi": "Mô -men xoắn"
        },
        {
            "bbox": [
                396.4746590909091,
                335.0568601421188,
                111.97709132996636,
                12.514548126615068
            ],
            "text": ", there must be",
            "font": {
                "color": [
                    0,
                    0,
                    0,
                    255
                ],
                "name": "/Times-Roman",
                "size": 1
            },
            "text_vi": ", phải có"
        },
        {
            "bbox": [
                110.43858013468014,
                350.9489421834626,
                398.1074392255892,
                12.514548126614955
            ],
            "text": "some type of antitorque system. Finally there is the",
            "font": {
                "color": [
                    0,
                    0,
                    0,
                    255
                ],
                "name": "/Times-Roman",
                "size": 1
            },
            "text_vi": "Một số loại hệ thống chống đối. Cuối cùng cũng có"
        },
        {
            "bbox": [
                110.43858013468014,
                366.8410109819122,
                398.1944261784512,
                12.51456136950901
            ],
            "text": "landing gear, which could be skids, wheels, skis, or",
            "font": {
                "color": [
                    0,
                    0,
                    0,
                    255
                ],
                "name": "/Times-Roman",
                "size": 1
            },
            "text_vi": "thiết bị hạ cánh, có thể là trượt, bánh xe, ván trượt hoặc"
        },
        {
            "bbox": [
                110.43858013468014,
                382.73309302325583,
                397.7595086700336,
                12.514548126614955
            ],
            "text": "floats. This chapter is an introduction to these compo-",
            "font": {
                "color": [
                    0,
                    0,
                    0,
                    255
                ],
                "name": "/Times-Roman",
                "size": 1
            },
            "text_vi": "phao. Chương này là phần giới thiệu về các compo-"
        },
        {
            "bbox": [
                110.43858013468014,
                398.6251750645995,
                135.33029444444446,
                12.514548126614955
            ],
            "text": "nents. [Figure 1-1]",
            "font": {
                "color": [
                    0,
                    0,
                    0,
                    255
                ],
                "name": "/Times-Roman",
                "size": 1
            },
            "text_vi": "Nents. [Hình 1-1]"
        },
        {
            "bbox": [
                542.6978114478114,
                192.2500594315245,
                275.3512373737374,
                19.59946996124029
            ],
            "text": "THE MAIN ROTOR SYSTEM",
            "font": {
                "color": [
                    0,
                    0,
                    0,
                    255
                ],
                "name": "/Helvetica-Bold",
                "size": 1
            },
            "text_vi": "Hệ thống rôto chính"
        },
        {
            "bbox": [
                542.6978114478114,
                215.18207719638235,
                397.72514183501687,
                12.514548126615068
            ],
            "text": "The rotor system found on helicopters can consist of a",
            "font": {
                "color": [
                    0,
                    0,
                    0,
                    255
                ],
                "name": "/Times-Roman",
                "size": 1
            },
            "text_vi": "Hệ thống rôto được tìm thấy trên máy bay trực thăng có thể bao gồm một"
        },
        {
            "bbox": [
                542.6978114478114,
                232.39791892764867,
                397.85005723905715,
                12.51454812661484
            ],
            "text": "single main rotor or dual rotors. With most dual rotors,",
            "font": {
                "color": [
                    0,
                    0,
                    0,
                    255
                ],
                "name": "/Times-Roman",
                "size": 1
            },
            "text_vi": "Rôto chính đơn hoặc cánh quạt kép. Với hầu hết các cánh quạt kép,"
        },
        {
            "bbox": [
                542.6978114478114,
                249.61376065891477,
                397.72873106060604,
                12.514548126614955
            ],
            "text": "the rotors turn in opposite directions so the torque from",
            "font": {
                "color": [
                    0,
                    0,
                    0,
                    255
                ],
                "name": "/Times-Roman",
                "size": 1
            },
            "text_vi": "Các cánh quạt quay theo hướng ngược lại để mô -men xoắn từ"
        },
        {
            "bbox": [
                542.6978114478114,
                266.82960239018087,
                398.24859932659945,
                12.514548126614955
            ],
            "text": "one rotor is opposed by the torque of the other. This",
            "font": {
                "color": [
                    0,
                    0,
                    0,
                    255
                ],
                "name": "/Times-Roman",
                "size": 1
            },
            "text_vi": "Một cánh quạt bị phản đối bởi mô -men xoắn của người kia. Cái này"
        },
        {
            "bbox": [
                542.6978114478114,
                284.0454441214471,
                314.9136662457912,
                12.51454812661484
            ],
            "text": "cancels the turning tendencies. [Figure 1-2]",
            "font": {
                "color": [
                    0,
                    0,
                    0,
                    255
                ],
                "name": "/Times-Roman",
                "size": 1
            },
            "text_vi": "hủy bỏ xu hướng quay đầu. [Hình 1-2]"
        },
        {
            "bbox": [
                542.6978114478114,
                315.82823094315245,
                398.109257996633,
                12.514548126615068
            ],
            "text": "In general, a rotor system can be classified as either",
            "font": {
                "color": [
                    0,
                    0,
                    0,
                    255
                ],
                "name": "/Times-Roman",
                "size": 1
            },
            "text_vi": "Nói chung, một hệ thống rôto có thể được phân loại là"
        },
        {
            "bbox": [
                542.6978114478114,
                331.72027325581394,
                398.21246548821557,
                12.514548126614955
            ],
            "text": "fully articulated, semirigid, or rigid. There are varia-",
            "font": {
                "color": [
                    0,
                    0,
                    0,
                    255
                ],
                "name": "/Times-Roman",
                "size": 1
            },
            "text_vi": "khớp nối đầy đủ, semirigid, hoặc cứng nhắc. Có varia-"
        },
        {
            "bbox": [
                542.6978114478114,
                347.6123552971576,
                397.72693644781145,
                12.514548126615068
            ],
            "text": "tions and combinations of these systems, which will be",
            "font": {
                "color": [
                    0,
                    0,
                    0,
                    255
                ],
                "name": "/Times-Roman",
                "size": 1
            },
            "text_vi": "tions và sự kết hợp của các hệ thống này, sẽ"
        },
        {
            "bbox": [
                542.6978114478114,
                363.5044240956072,
                400.2146321548821,
                12.51456136950901
            ],
            "text": "discussed in greater detail in Chapter 5—Helicopter",
            "font": {
                "color": [
                    0,
                    0,
                    0,
                    255
                ],
                "name": "/Times-Roman",
                "size": 1
            },
            "text_vi": "thảo luận chi tiết hơn trong Chương 5"
        },
        {
            "bbox": [
                542.6978114478114,
                379.39650613695096,
                64.92287878787886,
                12.514548126614955
            ],
            "text": "Systems.",
            "font": {
                "color": [
                    0,
                    0,
                    0,
                    255
                ],
                "name": "/Times-Roman",
                "size": 1
            },
            "text_vi": "Hệ thống."
        },
        {
            "bbox": [
                542.6978114478114,
                415.511930878553,
                354.0236283670034,
                13.47465794573634
            ],
            "text": "FULLY ARTICULATED ROTOR SYSTEM",
            "font": {
                "color": [
                    0,
                    0,
                    0,
                    255
                ],
                "name": "/Helvetica-Bold",
                "size": 1
            },
            "text_vi": "Hệ thống rôto được khớp nối hoàn toàn"
        },
        {
            "bbox": [
                542.6978114478114,
                435.0140788113695,
                398.17624537037034,
                12.514548126615068
            ],
            "text": "A fully articulated rotor system usually consists of",
            "font": {
                "color": [
                    0,
                    0,
                    0,
                    255
                ],
                "name": "/Times-Roman",
                "size": 1
            },
            "text_vi": "Một hệ thống rôto được khớp nối hoàn toàn thường bao gồm"
        },
        {
            "bbox": [
                542.6978114478114,
                450.90616085271324,
                397.88639814814815,
                12.514548126614955
            ],
            "text": "three or more rotor blades. The blades are allowed to",
            "font": {
                "color": [
                    0,
                    0,
                    0,
                    255
                ],
                "name": "/Times-Roman",
                "size": 1
            },
            "text_vi": "Ba hoặc nhiều lưỡi cánh quạt. Các lưỡi dao được phép"
        },
        {
            "bbox": [
                542.6978114478114,
                466.79702454780363,
                31.428656986531905,
                12.514548126614955
            ],
            "text": "flap",
            "font": {
                "color": [
                    0,
                    0,
                    0,
                    255
                ],
                "name": "/Times-Bold",
                "size": 1
            },
            "text_vi": "vạt"
        },
        {
            "bbox": [
                574.0360475589225,
                466.79702454780363,
                10.025086700336715,
                12.514548126614955
            ],
            "text": ", ",
            "font": {
                "color": [
                    0,
                    0,
                    0,
                    255
                ],
                "name": "/Times-Roman",
                "size": 1
            },
            "text_vi": "Thì "
        },
        {
            "bbox": [
                584.0607201178451,
                466.79702454780363,
                57.46519276094273,
                12.514548126614955
            ],
            "text": "feather",
            "font": {
                "color": [
                    0,
                    0,
                    0,
                    255
                ],
                "name": "/Times-Bold",
                "size": 1
            },
            "text_vi": "lông vũ"
        },
        {
            "bbox": [
                641.3778918350168,
                466.79702454780363,
                42.25640151515154,
                12.514548126614955
            ],
            "text": ", and ",
            "font": {
                "color": [
                    0,
                    0,
                    0,
                    255
                ],
                "name": "/Times-Roman",
                "size": 1
            },
            "text_vi": ", Và "
        },
        {
            "bbox": [
                683.6298068181818,
                466.79702454780363,
                85.35711658249159,
                12.514548126614955
            ],
            "text": "lead or lag",
            "font": {
                "color": [
                    0,
                    0,
                    0,
                    255
                ],
                "name": "/Times-Bold",
                "size": 1
            },
            "text_vi": "chì hoặc độ trễ"
        },
        {
            "bbox": [
                773.9685269360269,
                466.79702454780363,
                166.7661885521885,
                12.514548126614955
            ],
            "text": "independently of each",
            "font": {
                "color": [
                    0,
                    0,
                    0,
                    255
                ],
                "name": "/Times-Roman",
                "size": 1
            },
            "text_vi": "độc lập với mỗi"
        },
        {
            "bbox": [
                542.6979667508417,
                482.6891065891473,
                397.7414141414141,
                12.514548126614955
            ],
            "text": "other. Each rotor blade is attached to the rotor hub by a",
            "font": {
                "color": [
                    0,
                    0,
                    0,
                    255
                ],
                "name": "/Times-Roman",
                "size": 1
            },
            "text_vi": "khác. Mỗi lưỡi rôto được gắn vào trung tâm rôto bởi một"
        },
        {
            "bbox": [
                542.6979667508417,
                498.5811753875969,
                397.813888888889,
                12.514561369509124
            ],
            "text": "horizontal hinge, called the flapping hinge, which per-",
            "font": {
                "color": [
                    0,
                    0,
                    0,
                    255
                ],
                "name": "/Times-Roman",
                "size": 1
            },
            "text_vi": "bản lề ngang, được gọi là bản lề vỗ, mà per-"
        },
        {
            "bbox": [
                542.6979667508417,
                514.4732574289405,
                398.0928821548821,
                12.514548126615068
            ],
            "text": "mits the blades to flap up and down. Each blade can",
            "font": {
                "color": [
                    0,
                    0,
                    0,
                    255
                ],
                "name": "/Times-Roman",
                "size": 1
            },
            "text_vi": "Mits các lưỡi dao để vỗ lên và xuống. Mỗi lưỡi dao có thể"
        },
        {
            "bbox": [
                542.6979667508417,
                530.3653394702842,
                398.10383964646473,
                12.514548126615011
            ],
            "text": "move up and down independently of the others. The",
            "font": {
                "color": [
                    0,
                    0,
                    0,
                    255
                ],
                "name": "/Times-Roman",
                "size": 1
            },
            "text_vi": "Di chuyển lên và xuống độc lập với những người khác. Các"
        },
        {
            "bbox": [
                542.6979667508417,
                546.2574215116279,
                398.1001468855219,
                12.514548126615011
            ],
            "text": "flapping hinge may be located at varying distances",
            "font": {
                "color": [
                    0,
                    0,
                    0,
                    255
                ],
                "name": "/Times-Roman",
                "size": 1
            },
            "text_vi": "Bản lề vỗ có thể được đặt ở các khoảng cách khác nhau"
        },
        {
            "bbox": [
                542.6979667508417,
                562.1494903100775,
                398.08572095959596,
                12.514561369509067
            ],
            "text": "from the rotor hub, and there may be more than one.",
            "font": {
                "color": [
                    0,
                    0,
                    0,
                    255
                ],
                "name": "/Times-Roman",
                "size": 1
            },
            "text_vi": "Từ trung tâm rôto, và có thể có nhiều hơn một."
        },
        {
            "bbox": [
                542.6979667508417,
                578.0415723514211,
                397.7957702020203,
                12.514548126615011
            ],
            "text": "The position is chosen by each manufacturer, primarily",
            "font": {
                "color": [
                    0,
                    0,
                    0,
                    255
                ],
                "name": "/Times-Roman",
                "size": 1
            },
            "text_vi": "Vị trí được chọn bởi mỗi nhà sản xuất, chủ yếu"
        },
        {
            "bbox": [
                542.6979667508417,
                593.9336543927649,
                255.58763257575765,
                12.514548126614955
            ],
            "text": "with regard to stability and control.",
            "font": {
                "color": [
                    0,
                    0,
                    0,
                    255
                ],
                "name": "/Times-Roman",
                "size": 1
            },
            "text_vi": "liên quan đến sự ổn định và kiểm soát."
        },
        {
            "bbox": [
                110.43771043771044,
                873.6203456072351,
                185.43180092592593,
                8.938953488372107
            ],
            "text": "Payload—The term used for pas-",
            "font": {
                "color": [
                    0,
                    0,
                    0,
                    255
                ],
                "name": "/Times-Bold",
                "size": 1
            },
            "text_vi": "Tải trọng- Thuật ngữ được sử dụng cho PAS-"
        },
        {
            "bbox": [
                110.43771043771044,
                884.8764744832041,
                160.94958964646463,
                8.938954812661507
            ],
            "text": "sengers, baggage, and cargo.",
            "font": {
                "color": [
                    0,
                    0,
                    0,
                    255
                ],
                "name": "/Times-Bold",
                "size": 1
            },
            "text_vi": "Sengers, hành lý và hàng hóa."
        },
        {
            "bbox": [
                110.43771043771044,
                909.379144509044,
                191.52744486531986,
                8.938953488372093
            ],
            "text": "Torque—In helicopters with a sin-",
            "font": {
                "color": [
                    0,
                    0,
                    0,
                    255
                ],
                "name": "/Times-Bold",
                "size": 1
            },
            "text_vi": "Mô-men xoắn- trực thăng với một tội lỗi-"
        },
        {
            "bbox": [
                110.43771043771044,
                920.6322897609818,
                171.35099284511784,
                8.938953488372093
            ],
            "text": "gle, main rotor system, the ten-",
            "font": {
                "color": [
                    0,
                    0,
                    0,
                    255
                ],
                "name": "/Times-Bold",
                "size": 1
            },
            "text_vi": "gle, hệ thống rôto chính, mười-"
        },
        {
            "bbox": [
                110.43771043771044,
                931.8854363372093,
                181.35509638047137,
                8.938948191214465
            ],
            "text": "dency of the helicopter to turn in",
            "font": {
                "color": [
                    0,
                    0,
                    0,
                    255
                ],
                "name": "/Times-Bold",
                "size": 1
            },
            "text_vi": "dency của máy bay trực thăng để quay vào"
        },
        {
            "bbox": [
                110.43771043771044,
                943.1385829134367,
                185.32826557239053,
                8.938953488372093
            ],
            "text": "the opposite direction of the main",
            "font": {
                "color": [
                    0,
                    0,
                    0,
                    255
                ],
                "name": "/Times-Bold",
                "size": 1
            },
            "text_vi": "hướng ngược lại của chính"
        },
        {
            "bbox": [
                110.43771043771044,
                954.3917334625323,
                82.50473484848486,
                8.938953488372093
            ],
            "text": "rotor rotation. ",
            "font": {
                "color": [
                    0,
                    0,
                    0,
                    255
                ],
                "name": "/Times-Bold",
                "size": 1
            },
            "text_vi": "Xoay vòng quay. "
        },
        {
            "bbox": [
                323.1161683501684,
                873.6104134366925,
                158.66273526936027,
                8.938953488372078
            ],
            "text": "Blade Flap—The upward or",
            "font": {
                "color": [
                    0,
                    0,
                    0,
                    255
                ],
                "name": "/Times-Bold",
                "size": 1
            },
            "text_vi": "Lưỡi dao vạt - lên trên hoặc"
        },
        {
            "bbox": [
                323.1161683501684,
                884.8665423126615,
                186.3248623737373,
                8.938956136950907
            ],
            "text": "downward movement of the rotor",
            "font": {
                "color": [
                    0,
                    0,
                    0,
                    255
                ],
                "name": "/Times-Bold",
                "size": 1
            },
            "text_vi": "Chuyển động xuống của rôto"
        },
        {
            "bbox": [
                323.1161683501684,
                896.1226711886304,
                126.97320370370369,
                8.938953488372107
            ],
            "text": "blades during rotation.",
            "font": {
                "color": [
                    0,
                    0,
                    0,
                    255
                ],
                "name": "/Times-Bold",
                "size": 1
            },
            "text_vi": "Lưỡi dao trong quá trình xoay."
        },
        {
            "bbox": [
                323.1161683501684,
                918.6359248062015,
                193.48169191919186,
                8.938953488372093
            ],
            "text": "Blade Feather or Feathering—The",
            "font": {
                "color": [
                    0,
                    0,
                    0,
                    255
                ],
                "name": "/Times-Bold",
                "size": 1
            },
            "text_vi": "Lông lưỡi hoặc lông vũ -"
        },
        {
            "bbox": [
                323.1161683501684,
                929.8920510335918,
                176.450178030303,
                8.938953488372093
            ],
            "text": "rotation of the blade around the",
            "font": {
                "color": [
                    0,
                    0,
                    0,
                    255
                ],
                "name": "/Times-Bold",
                "size": 1
            },
            "text_vi": "vòng quay của lưỡi kiếm xung quanh"
        },
        {
            "bbox": [
                323.1161683501684,
                941.1481719638243,
                159.925901094276,
                8.938953488372093
            ],
            "text": "spanwise (pitch change) axis.",
            "font": {
                "color": [
                    0,
                    0,
                    0,
                    255
                ],
                "name": "/Times-Bold",
                "size": 1
            },
            "text_vi": "Trục SCORWIMER (thay đổi cao độ)."
        },
        {
            "bbox": [
                535.7946090067339,
                873.6094202196382,
                189.1720328282829,
                8.938953488372078
            ],
            "text": "Blade Lead or Lag—The fore and",
            "font": {
                "color": [
                    0,
                    0,
                    0,
                    255
                ],
                "name": "/Times-Bold",
                "size": 1
            },
            "text_vi": "Blade chì hoặc trễ - trước và"
        },
        {
            "bbox": [
                535.7946090067339,
                884.8655490956072,
                178.61919191919196,
                8.938948191214479
            ],
            "text": "aft movement of the blade in the",
            "font": {
                "color": [
                    0,
                    0,
                    0,
                    255
                ],
                "name": "/Times-Bold",
                "size": 1
            },
            "text_vi": "phía sau chuyển động của lưỡi kiếm trong"
        },
        {
            "bbox": [
                535.7946090067339,
                896.1216713501292,
                180.64330808080808,
                8.938953488372107
            ],
            "text": "plane of rotation. It is sometimes",
            "font": {
                "color": [
                    0,
                    0,
                    0,
                    255
                ],
                "name": "/Times-Bold",
                "size": 1
            },
            "text_vi": "mặt phẳng của vòng quay. Nó đôi khi là"
        },
        {
            "bbox": [
                535.7946090067339,
                907.3777975775193,
                150.38515277777788,
                8.938953488372093
            ],
            "text": "called hunting or dragging.",
            "font": {
                "color": [
                    0,
                    0,
                    0,
                    255
                ],
                "name": "/Times-Bold",
                "size": 1
            },
            "text_vi": "được gọi là săn bắn hoặc kéo."
        },
        {
            "bbox": [
                265.8178573232323,
                558.275798126615,
                83.64276094276096,
                9.651421188630536
            ],
            "text": "Landing Gear",
            "font": {
                "color": [
                    0,
                    0,
                    0,
                    255
                ],
                "name": "/CDQEXC+Helvetica",
                "size": 1
            },
            "text_vi": "Thiết bị hạ cánh"
        },
        {
            "bbox": [
                410.85347643097646,
                450.18290019379845,
                62.13501683501681,
                9.65142118863048
            ],
            "text": "Tail RotorGLYPH<.notdef>",
            "font": {
                "color": [
                    0,
                    0,
                    0,
                    255
                ],
                "name": "/CDQEXC+Helvetica",
                "size": 1
            },
            "text_vi": "Đuôi rotorglyph <.notdef>"
        },
        {
            "bbox": [
                416.99105218855215,
                462.76364954780365,
                46.02489856902366,
                9.65142118863048
            ],
            "text": "System",
            "font": {
                "color": [
                    0,
                    0,
                    0,
                    255
                ],
                "name": "/CDQEXC+Helvetica",
                "size": 1
            },
            "text_vi": "Hệ thống"
        },
        {
            "bbox": [
                318.7965871212121,
                448.12947028423775,
                71.3427781986532,
                9.651407945736423
            ],
            "text": "Main RotorGLYPH<.notdef>",
            "font": {
                "color": [
                    0,
                    0,
                    0,
                    255
                ],
                "name": "/CDQEXC+Helvetica",
                "size": 1
            },
            "text_vi": "Rotorglyph chính <.notdef>"
        },
        {
            "bbox": [
                329.5366372053872,
                460.71021963824296,
                46.024915824915865,
                9.65140794573631
            ],
            "text": "System",
            "font": {
                "color": [
                    0,
                    0,
                    0,
                    255
                ],
                "name": "/CDQEXC+Helvetica",
                "size": 1
            },
            "text_vi": "Hệ thống"
        },
        {
            "bbox": [
                124.54353956228955,
                451.83826195090444,
                36.057905555555564,
                9.65142118863048
            ],
            "text": "Cabin",
            "font": {
                "color": [
                    0,
                    0,
                    0,
                    255
                ],
                "name": "/CDQEXC+Helvetica",
                "size": 1
            },
            "text_vi": "Cabin"
        },
        {
            "bbox": [
                169.2521,
                525.531484496124,
                9.44610664983162,
                9.514529392764928
            ],
            "text": "A",
            "font": {
                "color": [
                    0,
                    0,
                    0,
                    255
                ],
                "name": "/CDQEXC+Helvetica",
                "size": 1
            },
            "text_vi": "MỘT"
        },
        {
            "bbox": [
                178.4580046296296,
                525.576430878553,
                11.737216329966344,
                9.604567829457324
            ],
            "text": "irf",
            "font": {
                "color": [
                    0,
                    0,
                    0,
                    255
                ],
                "name": "/CDQEXC+Helvetica",
                "size": 1
            },
            "text_vi": "Irf"
        },
        {
            "bbox": [
                189.95501893939394,
                525.767459625323,
                12.510142255892248,
                9.582107881136949
            ],
            "text": "ra",
            "font": {
                "color": [
                    0,
                    0,
                    0,
                    255
                ],
                "name": "/CDQEXC+Helvetica",
                "size": 1
            },
            "text_vi": "ra"
        },
        {
            "bbox": [
                202.22495917508417,
                526.0485003229974,
                11.737233585858604,
                9.4809586563307
            ],
            "text": "m",
            "font": {
                "color": [
                    0,
                    0,
                    0,
                    255
                ],
                "name": "/CDQEXC+Helvetica",
                "size": 1
            },
            "text_vi": "m"
        },
        {
            "bbox": [
                213.72199074074075,
                526.1610119509044,
                7.914087121212106,
                9.537002583979358
            ],
            "text": "e",
            "font": {
                "color": [
                    0,
                    0,
                    0,
                    255
                ],
                "name": "/CDQEXC+Helvetica",
                "size": 1
            },
            "text_vi": "e"
        },
        {
            "bbox": [
                355.24532828282827,
                522.3566728036176,
                81.55824915824917,
                9.651421188630536
            ],
            "text": "Transmission",
            "font": {
                "color": [
                    0,
                    0,
                    0,
                    255
                ],
                "name": "/CDQEXC+Helvetica",
                "size": 1
            },
            "text_vi": "Quá trình lây truyền"
        },
        {
            "bbox": [
                432.65560606060603,
                549.1735332687339,
                72.88890614478112,
                9.65142118863048
            ],
            "text": "PowerplantGLYPH<.notdef>",
            "font": {
                "color": [
                    0,
                    0,
                    0,
                    255
                ],
                "name": "/CDQEXC+Helvetica",
                "size": 1
            },
            "text_vi": "Powerplantglyph <.notdef>"
        },
        {
            "bbox": [
                467.18121254208756,
                561.7542826227391,
                3.8377104377103706,
                9.651421188630536
            ],
            "text": "GLYPH<.notdef>",
            "font": {
                "color": [
                    0,
                    0,
                    0,
                    255
                ],
                "name": "/CDQEXC+Helvetica",
                "size": 1
            },
            "text_vi": "Glyph <.notdef>"
        },
        {
            "bbox": [
                110.43771043771044,
                840.7635335917313,
                35.58068005050505,
                9.799754844961257
            ],
            "text": "Figure",
            "font": {
                "color": [
                    0,
                    0,
                    0,
                    255
                ],
                "name": "/Helvetica-Bold",
                "size": 1
            },
            "text_vi": "Nhân vật"
        },
        {
            "bbox": [
                560.0481797138048,
                840.7635335917313,
                42.049917508417366,
                9.799754844961257
            ],
            "text": "1-2. Helicopters can have a single main rotor or a dual rotor system.",
            "font": {
                "color": [
                    0,
                    0,
                    0,
                    255
                ],
                "name": "/Helvetica-Bold",
                "size": 1
            },
            "text_vi": "1-2. Máy bay trực thăng có thể có một rôto chính duy nhất hoặc hệ thống rôto kép."
        },
        {
            "bbox": [
                110.43771043771044,
                582.3014670542636,
                398.05890530303026,
                9.799728359173116
            ],
            "text": "Figure 1-1. The major components of a helicopter are the",
            "font": {
                "color": [
                    0,
                    0,
                    0,
                    255
                ],
                "name": "/Helvetica-Bold",
                "size": 1
            },
            "text_vi": "Hình 1-1. Các thành phần chính của máy bay trực thăng là"
        },
        {
            "bbox": [
                110.43771043771044,
                595.5443611111111,
                397.8656393097643,
                9.799728359173116
            ],
            "text": "cabin, airframe, landing gear, powerplant, transmission, main",
            "font": {
                "color": [
                    0,
                    0,
                    0,
                    255
                ],
                "name": "/Helvetica-Bold",
                "size": 1
            },
            "text_vi": "cabin, khung máy bay, thiết bị hạ cánh, động cơ, truyền, chính"
        },
        {
            "bbox": [
                110.43771043771044,
                608.7872551679586,
                230.86175084175085,
                9.799728359173116
            ],
            "text": "rotor system, and tail rotor system.",
            "font": {
                "color": [
                    0,
                    0,
                    0,
                    255
                ],
                "name": "/Helvetica-Bold",
                "size": 1
            },
            "text_vi": "Hệ thống rôto, và hệ thống cánh quạt đuôi."
        }
    ]
}