{
    "metadata": {
        "page_hash": "3b502fb49e720be3b04164f73de8ba377031beb01786fab5fcfc74dfb7d2458d",
        "original_filename": "OTC_STKAF_2002.pdf",
        "page_no": 76,
        "num_pages": 91,
        "original_width": 595,
        "original_height": 842,
        "coco_width": 1025,
        "coco_height": 1025,
        "collection": "ann_reports_00_04_fancy",
        "doc_category": "financial_reports"
    },
    "cells": [
        {
            "bbox": [
                123.56556226890757,
                139.3116820071259,
                15.810027226890753,
                10.292631235154317
            ],
            "text": "31",
            "font": {
                "color": [
                    0,
                    0,
                    0,
                    255
                ],
                "name": "/CLEPKB+HelveticaNeue-BoldCond",
                "size": 1
            },
            "text_vi": "31"
        },
        {
            "bbox": [
                143.32809457983194,
                139.3116820071259,
                205.03624365546221,
                10.292631235154317
            ],
            "text": "Interest in joint venture entities",
            "font": {
                "color": [
                    0,
                    0,
                    0,
                    255
                ],
                "name": "/CLEPKB+HelveticaNeue-BoldCond",
                "size": 1
            },
            "text_vi": "Quan tâm đến các thực thể liên doanh"
        },
        {
            "bbox": [
                143.09844462184876,
                206.53545486935877,
                112.82905075630254,
                9.209101543943007
            ],
            "text": "Subiaco Joint Venture",
            "font": {
                "color": [
                    0,
                    0,
                    0,
                    255
                ],
                "name": "/CLEPKC+HelveticaNeue-LightCond",
                "size": 1
            },
            "text_vi": "Liên doanh Subiaco"
        },
        {
            "bbox": [
                506.53708403361344,
                206.53545486935877,
                113.07214285714286,
                9.209101543943007
            ],
            "text": "Property development",
            "font": {
                "color": [
                    0,
                    0,
                    0,
                    255
                ],
                "name": "/CLEPKC+HelveticaNeue-LightCond",
                "size": 1
            },
            "text_vi": "Phát triển tài sản"
        },
        {
            "bbox": [
                688.020655462185,
                206.53545486935877,
                14.169289915966374,
                9.209101543943007
            ],
            "text": "30",
            "font": {
                "color": [
                    0,
                    0,
                    0,
                    255
                ],
                "name": "/CLEPKC+HelveticaNeue-LightCond",
                "size": 1
            },
            "text_vi": "30"
        },
        {
            "bbox": [
                705.7322764705882,
                206.53545486935877,
                25.401343277310957,
                9.209101543943007
            ],
            "text": "June",
            "font": {
                "color": [
                    0,
                    0,
                    0,
                    255
                ],
                "name": "/CLEPKC+HelveticaNeue-LightCond",
                "size": 1
            },
            "text_vi": "Tháng sáu"
        },
        {
            "bbox": [
                834.9749054621849,
                206.53545486935877,
                42.19194579831935,
                9.209101543943007
            ],
            "text": "33.33%",
            "font": {
                "color": [
                    0,
                    0,
                    0,
                    255
                ],
                "name": "/CLEPKC+HelveticaNeue-LightCond",
                "size": 1
            },
            "text_vi": "33,33%"
        },
        {
            "bbox": [
                143.09844462184876,
                221.75220071258912,
                170.13535369747896,
                9.209101543943007
            ],
            "text": "Elizabeth City Centre Partnership",
            "font": {
                "color": [
                    0,
                    0,
                    0,
                    255
                ],
                "name": "/CLEPKC+HelveticaNeue-LightCond",
                "size": 1
            },
            "text_vi": "Quan hệ đối tác Trung tâm Thành phố Elizabeth"
        },
        {
            "bbox": [
                511.40728109243696,
                221.75220071258912,
                103.34930294117646,
                9.209101543943007
            ],
            "text": "Property investment",
            "font": {
                "color": [
                    0,
                    0,
                    0,
                    255
                ],
                "name": "/CLEPKC+HelveticaNeue-LightCond",
                "size": 1
            },
            "text_vi": "Đầu tư bất động sản"
        },
        {
            "bbox": [
                688.0396911764706,
                221.75220071258912,
                14.172649159663933,
                9.209101543943007
            ],
            "text": "30",
            "font": {
                "color": [
                    0,
                    0,
                    0,
                    255
                ],
                "name": "/CLEPKC+HelveticaNeue-LightCond",
                "size": 1
            },
            "text_vi": "30"
        },
        {
            "bbox": [
                705.7554983193278,
                221.75220071258912,
                25.407407142857096,
                9.209101543943007
            ],
            "text": "June",
            "font": {
                "color": [
                    0,
                    0,
                    0,
                    255
                ],
                "name": "/CLEPKC+HelveticaNeue-LightCond",
                "size": 1
            },
            "text_vi": "Tháng sáu"
        },
        {
            "bbox": [
                843.7884411764707,
                221.75220071258912,
                24.629285714285743,
                9.209101543943007
            ],
            "text": "50%",
            "font": {
                "color": [
                    0,
                    0,
                    0,
                    255
                ],
                "name": "/CLEPKC+HelveticaNeue-LightCond",
                "size": 1
            },
            "text_vi": "50%"
        },
        {
            "bbox": [
                143.09844462184876,
                236.96894655581957,
                168.8467994957983,
                9.209101543943007
            ],
            "text": "Elizabeth City Centre Pty Limited",
            "font": {
                "color": [
                    0,
                    0,
                    0,
                    255
                ],
                "name": "/CLEPKC+HelveticaNeue-LightCond",
                "size": 1
            },
            "text_vi": "Trung tâm thành phố Elizabeth Pty Limited"
        },
        {
            "bbox": [
                507.6865827731093,
                236.96894655581957,
                110.72930294117646,
                9.209101543943007
            ],
            "text": "Agent for Partnership",
            "font": {
                "color": [
                    0,
                    0,
                    0,
                    255
                ],
                "name": "/CLEPKC+HelveticaNeue-LightCond",
                "size": 1
            },
            "text_vi": "Đại lý cho quan hệ đối tác"
        },
        {
            "bbox": [
                687.9797071428573,
                236.96894655581957,
                14.17264915966382,
                9.209101543943007
            ],
            "text": "30",
            "font": {
                "color": [
                    0,
                    0,
                    0,
                    255
                ],
                "name": "/CLEPKC+HelveticaNeue-LightCond",
                "size": 1
            },
            "text_vi": "30"
        },
        {
            "bbox": [
                705.6955142857144,
                236.96894655581957,
                25.407407142857096,
                9.209101543943007
            ],
            "text": "June",
            "font": {
                "color": [
                    0,
                    0,
                    0,
                    255
                ],
                "name": "/CLEPKC+HelveticaNeue-LightCond",
                "size": 1
            },
            "text_vi": "Tháng sáu"
        },
        {
            "bbox": [
                843.7284571428572,
                236.96894655581957,
                24.62928571428563,
                9.209101543943007
            ],
            "text": "50%",
            "font": {
                "color": [
                    0,
                    0,
                    0,
                    255
                ],
                "name": "/CLEPKC+HelveticaNeue-LightCond",
                "size": 1
            },
            "text_vi": "50%"
        },
        {
            "bbox": [
                143.09844462184876,
                316.096463182898,
                176.10817512605038,
                9.209101543942893
            ],
            "text": "Results of joint venture entities",
            "font": {
                "color": [
                    0,
                    0,
                    0,
                    255
                ],
                "name": "/CLFBCE+HelveticaNeue-MediumCondObl",
                "size": 1
            },
            "text_vi": "Kết quả của các thực thể liên doanh"
        },
        {
            "bbox": [
                143.09844462184876,
                331.31291686460804,
                405.5778709243697,
                9.209101543943007
            ],
            "text": "The consolidated entity’s share of the joint venture entities’ resuts consists of:",
            "font": {
                "color": [
                    0,
                    0,
                    0,
                    255
                ],
                "name": "/CLEPKC+HelveticaNeue-LightCond",
                "size": 1
            },
            "text_vi": "Các thực thể hợp nhất chia sẻ của các thực thể liên doanh, Resuts bao gồm:"
        },
        {
            "bbox": [
                143.09844462184876,
                346.5296627078385,
                166.52737092436976,
                9.209101543942893
            ],
            "text": "Revenue from ordinary activities",
            "font": {
                "color": [
                    0,
                    0,
                    0,
                    255
                ],
                "name": "/CLEPKC+HelveticaNeue-LightCond",
                "size": 1
            },
            "text_vi": "Doanh thu từ các hoạt động thông thường"
        },
        {
            "bbox": [
                757.572762605042,
                346.5296627078385,
                38.657142857142844,
                9.209101543942893
            ],
            "text": "12,874",
            "font": {
                "color": [
                    0,
                    0,
                    0,
                    255
                ],
                "name": "/CLFAHM+HelveticaNeue-MediumCond",
                "size": 1
            },
            "text_vi": "12.874"
        },
        {
            "bbox": [
                851.574031092437,
                346.5296627078385,
                38.65709117647066,
                9.209101543942893
            ],
            "text": "19,375",
            "font": {
                "color": [
                    0,
                    0,
                    0,
                    255
                ],
                "name": "/CLEPKC+HelveticaNeue-LightCond",
                "size": 1
            },
            "text_vi": "19.375"
        },
        {
            "bbox": [
                143.09844462184876,
                361.74640855106884,
                170.86310369747903,
                9.209101543943007
            ],
            "text": "Expenses from ordinary activities",
            "font": {
                "color": [
                    0,
                    0,
                    0,
                    255
                ],
                "name": "/CLEPKC+HelveticaNeue-LightCond",
                "size": 1
            },
            "text_vi": "Chi phí từ các hoạt động thông thường"
        },
        {
            "bbox": [
                760.8117453781513,
                361.74640855106884,
                39.203321428571485,
                9.209101543943007
            ],
            "text": "(7,427)",
            "font": {
                "color": [
                    0,
                    0,
                    0,
                    255
                ],
                "name": "/CLFAHM+HelveticaNeue-MediumCond",
                "size": 1
            },
            "text_vi": "(7.427)"
        },
        {
            "bbox": [
                848.3247983193278,
                361.74640855106884,
                45.15855420168077,
                9.209101543943007
            ],
            "text": "(13,656)",
            "font": {
                "color": [
                    0,
                    0,
                    0,
                    255
                ],
                "name": "/CLEPKC+HelveticaNeue-LightCond",
                "size": 1
            },
            "text_vi": "(13.656)"
        },
        {
            "bbox": [
                143.09844462184876,
                376.9631543942993,
                261.58292512605044,
                9.209101543943007
            ],
            "text": "Net profit - accounted for using the equity method",
            "font": {
                "color": [
                    0,
                    0,
                    0,
                    255
                ],
                "name": "/CLEPKC+HelveticaNeue-LightCond",
                "size": 1
            },
            "text_vi": "Lợi nhuận ròng - chiếm sử dụng phương pháp vốn chủ sở hữu"
        },
        {
            "bbox": [
                764.6013168067227,
                376.9631543942993,
                31.628536974789995,
                9.209101543943007
            ],
            "text": "5,447",
            "font": {
                "color": [
                    0,
                    0,
                    0,
                    255
                ],
                "name": "/CLFAHM+HelveticaNeue-MediumCond",
                "size": 1
            },
            "text_vi": "5.447"
        },
        {
            "bbox": [
                858.604049579832,
                376.9631543942993,
                31.628554201680686,
                9.209101543943007
            ],
            "text": "5,719",
            "font": {
                "color": [
                    0,
                    0,
                    0,
                    255
                ],
                "name": "/CLEPKC+HelveticaNeue-LightCond",
                "size": 1
            },
            "text_vi": "5.719"
        },
        {
            "bbox": [
                143.09844462184876,
                399.0813031472684,
                175.84460369747902,
                9.209174584323137
            ],
            "text": "Statement of Financial Position",
            "font": {
                "color": [
                    0,
                    0,
                    0,
                    255
                ],
                "name": "/CLFBCE+HelveticaNeue-MediumCondObl",
                "size": 1
            },
            "text_vi": "Báo cáo về tình hình tài chính"
        },
        {
            "bbox": [
                143.09844462184876,
                414.29804899049884,
                75.44878226890756,
                9.209174584323023
            ],
            "text": "Current assets",
            "font": {
                "color": [
                    0,
                    0,
                    0,
                    255
                ],
                "name": "/CLEPKC+HelveticaNeue-LightCond",
                "size": 1
            },
            "text_vi": "Tài sản hiện tại"
        },
        {
            "bbox": [
                764.6013168067227,
                414.29804899049884,
                31.628536974789995,
                9.209174584323023
            ],
            "text": "8,755",
            "font": {
                "color": [
                    0,
                    0,
                    0,
                    255
                ],
                "name": "/CLFAHM+HelveticaNeue-MediumCond",
                "size": 1
            },
            "text_vi": "8.755"
        },
        {
            "bbox": [
                851.5754953781512,
                414.29804899049884,
                38.65710840336146,
                9.209174584323023
            ],
            "text": "15,405",
            "font": {
                "color": [
                    0,
                    0,
                    0,
                    255
                ],
                "name": "/CLEPKC+HelveticaNeue-LightCond",
                "size": 1
            },
            "text_vi": "15.405"
        },
        {
            "bbox": [
                143.09844462184876,
                429.5147948337293,
                98.27115663865547,
                9.209174584323023
            ],
            "text": "Non current assets",
            "font": {
                "color": [
                    0,
                    0,
                    0,
                    255
                ],
                "name": "/CLEPKC+HelveticaNeue-LightCond",
                "size": 1
            },
            "text_vi": "Tài sản không hiện tại"
        },
        {
            "bbox": [
                757.572762605042,
                429.5147948337293,
                38.657142857142844,
                9.209174584323023
            ],
            "text": "60,806",
            "font": {
                "color": [
                    0,
                    0,
                    0,
                    255
                ],
                "name": "/CLFAHM+HelveticaNeue-MediumCond",
                "size": 1
            },
            "text_vi": "60.806"
        },
        {
            "bbox": [
                851.574031092437,
                429.5147948337293,
                38.65709117647066,
                9.209174584323023
            ],
            "text": "58,553",
            "font": {
                "color": [
                    0,
                    0,
                    0,
                    255
                ],
                "name": "/CLEPKC+HelveticaNeue-LightCond",
                "size": 1
            },
            "text_vi": "58.553"
        },
        {
            "bbox": [
                143.09844462184876,
                444.73154067695964,
                61.057782268907545,
                9.209174584323023
            ],
            "text": "Total assets",
            "font": {
                "color": [
                    0,
                    0,
                    0,
                    255
                ],
                "name": "/CLEPKC+HelveticaNeue-LightCond",
                "size": 1
            },
            "text_vi": "Tổng tài sản"
        },
        {
            "bbox": [
                757.572762605042,
                444.73154067695964,
                38.657142857142844,
                9.209174584323023
            ],
            "text": "69,561",
            "font": {
                "color": [
                    0,
                    0,
                    0,
                    255
                ],
                "name": "/CLFAHM+HelveticaNeue-MediumCond",
                "size": 1
            },
            "text_vi": "69,561"
        },
        {
            "bbox": [
                851.574031092437,
                444.73154067695964,
                38.65709117647066,
                9.209174584323023
            ],
            "text": "73,958",
            "font": {
                "color": [
                    0,
                    0,
                    0,
                    255
                ],
                "name": "/CLEPKC+HelveticaNeue-LightCond",
                "size": 1
            },
            "text_vi": "73.958"
        },
        {
            "bbox": [
                143.09844462184876,
                459.9482865201901,
                86.74135369747896,
                9.209174584323023
            ],
            "text": "Current liabilities",
            "font": {
                "color": [
                    0,
                    0,
                    0,
                    255
                ],
                "name": "/CLEPKC+HelveticaNeue-LightCond",
                "size": 1
            },
            "text_vi": "Nợ phải trả hiện tại"
        },
        {
            "bbox": [
                775.1427441176471,
                459.9482865201901,
                21.085697058823484,
                9.209174584323023
            ],
            "text": "584",
            "font": {
                "color": [
                    0,
                    0,
                    0,
                    255
                ],
                "name": "/CLFAHM+HelveticaNeue-MediumCond",
                "size": 1
            },
            "text_vi": "584"
        },
        {
            "bbox": [
                869.144012605042,
                459.9482865201901,
                21.085748739495784,
                9.209174584323023
            ],
            "text": "831",
            "font": {
                "color": [
                    0,
                    0,
                    0,
                    255
                ],
                "name": "/CLEPKC+HelveticaNeue-LightCond",
                "size": 1
            },
            "text_vi": "831"
        },
        {
            "bbox": [
                143.09844462184876,
                475.16503236342044,
                72.36792512605041,
                9.209174584323023
            ],
            "text": "Total liabilities",
            "font": {
                "color": [
                    0,
                    0,
                    0,
                    255
                ],
                "name": "/CLEPKC+HelveticaNeue-LightCond",
                "size": 1
            },
            "text_vi": "Tổng nợ phải trả"
        },
        {
            "bbox": [
                775.1427441176471,
                475.16503236342044,
                21.085697058823484,
                9.209174584323023
            ],
            "text": "584",
            "font": {
                "color": [
                    0,
                    0,
                    0,
                    255
                ],
                "name": "/CLFAHM+HelveticaNeue-MediumCond",
                "size": 1
            },
            "text_vi": "584"
        },
        {
            "bbox": [
                869.144012605042,
                475.16503236342044,
                21.085748739495784,
                9.209174584323023
            ],
            "text": "831",
            "font": {
                "color": [
                    0,
                    0,
                    0,
                    255
                ],
                "name": "/CLEPKC+HelveticaNeue-LightCond",
                "size": 1
            },
            "text_vi": "831"
        },
        {
            "bbox": [
                143.09844462184876,
                490.3817782066509,
                299.74367512605045,
                9.209174584323023
            ],
            "text": "Share of net assets before equity accounting adjustments",
            "font": {
                "color": [
                    0,
                    0,
                    0,
                    255
                ],
                "name": "/CLEPKC+HelveticaNeue-LightCond",
                "size": 1
            },
            "text_vi": "Chia sẻ tài sản ròng trước khi điều chỉnh kế toán vốn chủ sở hữu"
        },
        {
            "bbox": [
                757.572762605042,
                490.3817782066509,
                38.657142857142844,
                9.209174584323023
            ],
            "text": "68,977",
            "font": {
                "color": [
                    0,
                    0,
                    0,
                    255
                ],
                "name": "/CLFAHM+HelveticaNeue-MediumCond",
                "size": 1
            },
            "text_vi": "68.977"
        },
        {
            "bbox": [
                851.574031092437,
                490.3817782066509,
                38.65709117647066,
                9.209174584323023
            ],
            "text": "73,127",
            "font": {
                "color": [
                    0,
                    0,
                    0,
                    255
                ],
                "name": "/CLEPKC+HelveticaNeue-LightCond",
                "size": 1
            },
            "text_vi": "73.127"
        },
        {
            "bbox": [
                143.09844462184876,
                505.59852404988123,
                256.6922280672269,
                9.20917458432308
            ],
            "text": "Other adjustments arising from equity accounting",
            "font": {
                "color": [
                    0,
                    0,
                    0,
                    255
                ],
                "name": "/CLEPKC+HelveticaNeue-LightCond",
                "size": 1
            },
            "text_vi": "Các điều chỉnh khác phát sinh từ kế toán vốn chủ sở hữu"
        },
        {
            "bbox": [
                771.3545852941177,
                505.59852404988123,
                28.663427310924362,
                9.20917458432308
            ],
            "text": "(463)",
            "font": {
                "color": [
                    0,
                    0,
                    0,
                    255
                ],
                "name": "/CLFAHM+HelveticaNeue-MediumCond",
                "size": 1
            },
            "text_vi": "(463)"
        },
        {
            "bbox": [
                858.604049579832,
                505.59852404988123,
                31.628554201680686,
                9.20917458432308
            ],
            "text": "1,471",
            "font": {
                "color": [
                    0,
                    0,
                    0,
                    255
                ],
                "name": "/CLEPKC+HelveticaNeue-LightCond",
                "size": 1
            },
            "text_vi": "1.471"
        },
        {
            "bbox": [
                143.09844462184876,
                527.7167458432305,
                290.46303226890757,
                9.20917458432308
            ],
            "text": "Share of net assets after equity accounting adjustments",
            "font": {
                "color": [
                    0,
                    0,
                    0,
                    255
                ],
                "name": "/CLEPKC+HelveticaNeue-LightCond",
                "size": 1
            },
            "text_vi": "Chia sẻ tài sản ròng sau khi điều chỉnh kế toán vốn chủ sở hữu"
        },
        {
            "bbox": [
                757.572762605042,
                527.7167458432305,
                38.657142857142844,
                9.20917458432308
            ],
            "text": "68,574",
            "font": {
                "color": [
                    0,
                    0,
                    0,
                    255
                ],
                "name": "/CLFAHM+HelveticaNeue-MediumCond",
                "size": 1
            },
            "text_vi": "68.574"
        },
        {
            "bbox": [
                851.574031092437,
                527.7167458432305,
                38.65709117647066,
                9.20917458432308
            ],
            "text": "74,598",
            "font": {
                "color": [
                    0,
                    0,
                    0,
                    255
                ],
                "name": "/CLEPKC+HelveticaNeue-LightCond",
                "size": 1
            },
            "text_vi": "74.598"
        },
        {
            "bbox": [
                143.09844462184876,
                549.8349676365796,
                435.13449529411764,
                9.20917458432308
            ],
            "text": "Share of post-acquisition retained profits attributable to joint venture entities",
            "font": {
                "color": [
                    0,
                    0,
                    0,
                    255
                ],
                "name": "/CLFBCE+HelveticaNeue-MediumCondObl",
                "size": 1
            },
            "text_vi": "Chia sẻ lợi nhuận được giữ lại sau mua lại do các thực thể liên doanh"
        },
        {
            "bbox": [
                143.09844462184876,
                565.05171347981,
                432.8721394117647,
                9.209174584323023
            ],
            "text": "Share of joint venture entities’ retained profits at the beginning of the financial year",
            "font": {
                "color": [
                    0,
                    0,
                    0,
                    255
                ],
                "name": "/CLEPKC+HelveticaNeue-LightCond",
                "size": 1
            },
            "text_vi": "Chia sẻ của các thực thể liên doanh, người giữ lại lợi nhuận vào đầu năm tài chính"
        },
        {
            "bbox": [
                764.6013168067227,
                565.05171347981,
                31.628536974789995,
                9.209174584323023
            ],
            "text": "1,059",
            "font": {
                "color": [
                    0,
                    0,
                    0,
                    255
                ],
                "name": "/CLFAHM+HelveticaNeue-MediumCond",
                "size": 1
            },
            "text_vi": "1.059"
        },
        {
            "bbox": [
                865.8961924369748,
                565.05171347981,
                27.579804201680645,
                9.209174584323023
            ],
            "text": "(347)",
            "font": {
                "color": [
                    0,
                    0,
                    0,
                    255
                ],
                "name": "/CLEPKC+HelveticaNeue-LightCond",
                "size": 1
            },
            "text_vi": "(347)"
        },
        {
            "bbox": [
                143.09844462184876,
                580.2684593230404,
                206.59165789915963,
                9.209174584323023
            ],
            "text": "Share of joint venture entities’ net profit",
            "font": {
                "color": [
                    0,
                    0,
                    0,
                    255
                ],
                "name": "/CLEPKC+HelveticaNeue-LightCond",
                "size": 1
            },
            "text_vi": "Chia sẻ lợi nhuận ròng của liên doanh"
        },
        {
            "bbox": [
                764.6013168067227,
                580.2684593230404,
                31.628536974789995,
                9.209174584323023
            ],
            "text": "5,447",
            "font": {
                "color": [
                    0,
                    0,
                    0,
                    255
                ],
                "name": "/CLFAHM+HelveticaNeue-MediumCond",
                "size": 1
            },
            "text_vi": "5.447"
        },
        {
            "bbox": [
                858.604049579832,
                580.2684593230404,
                31.628554201680686,
                9.209174584323023
            ],
            "text": "5,719",
            "font": {
                "color": [
                    0,
                    0,
                    0,
                    255
                ],
                "name": "/CLEPKC+HelveticaNeue-LightCond",
                "size": 1
            },
            "text_vi": "5.719"
        },
        {
            "bbox": [
                143.09844462184876,
                595.4852051662708,
                240.71246084033615,
                9.209174584323023
            ],
            "text": "Distributions of joint venture entities’ net profit",
            "font": {
                "color": [
                    0,
                    0,
                    0,
                    255
                ],
                "name": "/CLEPKC+HelveticaNeue-LightCond",
                "size": 1
            },
            "text_vi": "Phân phối các thực thể liên doanh lợi nhuận ròng"
        },
        {
            "bbox": [
                760.8117453781513,
                595.4852051662708,
                39.203321428571485,
                9.209174584323023
            ],
            "text": "(5,095)",
            "font": {
                "color": [
                    0,
                    0,
                    0,
                    255
                ],
                "name": "/CLFAHM+HelveticaNeue-MediumCond",
                "size": 1
            },
            "text_vi": "(5.095)"
        },
        {
            "bbox": [
                855.3533525210084,
                595.4852051662708,
                38.13000000000011,
                9.209174584323023
            ],
            "text": "(4,313)",
            "font": {
                "color": [
                    0,
                    0,
                    0,
                    255
                ],
                "name": "/CLEPKC+HelveticaNeue-LightCond",
                "size": 1
            },
            "text_vi": "(4.313)"
        },
        {
            "bbox": [
                143.09844462184876,
                617.60339043943,
                2.7270822689075658,
                9.209174584323023
            ],
            "text": "I",
            "font": {
                "color": [
                    0,
                    0,
                    0,
                    255
                ],
                "name": "/CLEPKC+HelveticaNeue-LightCond",
                "size": 1
            },
            "text_vi": "TÔI"
        },
        {
            "bbox": [
                149.3825818067227,
                617.60339043943,
                112.44746651260502,
                9.209174584323023
            ],
            "text": "cannot read this copy",
            "font": {
                "color": [
                    0,
                    0,
                    0,
                    255
                ],
                "name": "/CLEPKC+HelveticaNeue-LightCond",
                "size": 1
            },
            "text_vi": "Không thể đọc bản sao này"
        },
        {
            "bbox": [
                764.6013168067227,
                617.60339043943,
                31.628536974789995,
                9.209174584323023
            ],
            "text": "1,411",
            "font": {
                "color": [
                    0,
                    0,
                    0,
                    255
                ],
                "name": "/CLFAHM+HelveticaNeue-MediumCond",
                "size": 1
            },
            "text_vi": "1.411"
        },
        {
            "bbox": [
                858.604049579832,
                617.60339043943,
                31.628554201680686,
                9.209174584323023
            ],
            "text": "1,059",
            "font": {
                "color": [
                    0,
                    0,
                    0,
                    255
                ],
                "name": "/CLEPKC+HelveticaNeue-LightCond",
                "size": 1
            },
            "text_vi": "1.059"
        },
        {
            "bbox": [
                143.09844462184876,
                639.721502672209,
                310.6321381512605,
                9.209174584323023
            ],
            "text": "Movements in carrying amount of joint venture entities",
            "font": {
                "color": [
                    0,
                    0,
                    0,
                    255
                ],
                "name": "/CLFBCE+HelveticaNeue-MediumCondObl",
                "size": 1
            },
            "text_vi": "Các phong trào mang theo số lượng các thực thể liên doanh"
        },
        {
            "bbox": [
                143.09844462184876,
                654.9383580760095,
                281.0520507563025,
                9.209186757719692
            ],
            "text": "Carrying amount at the beginning of the financial year",
            "font": {
                "color": [
                    0,
                    0,
                    0,
                    255
                ],
                "name": "/CLEPKC+HelveticaNeue-LightCond",
                "size": 1
            },
            "text_vi": "Mang theo số tiền vào đầu năm tài chính"
        },
        {
            "bbox": [
                757.572762605042,
                654.9383580760095,
                38.657142857142844,
                9.209186757719692
            ],
            "text": "74,598",
            "font": {
                "color": [
                    0,
                    0,
                    0,
                    255
                ],
                "name": "/CLFAHM+HelveticaNeue-MediumCond",
                "size": 1
            },
            "text_vi": "74.598"
        },
        {
            "bbox": [
                851.574031092437,
                654.9383580760095,
                38.65709117647066,
                9.209186757719692
            ],
            "text": "13,652",
            "font": {
                "color": [
                    0,
                    0,
                    0,
                    255
                ],
                "name": "/CLEPKC+HelveticaNeue-LightCond",
                "size": 1
            },
            "text_vi": "13.652"
        },
        {
            "bbox": [
                143.09844462184876,
                670.15510391924,
                170.11631798319328,
                9.209186757719692
            ],
            "text": "Contributions to the partnerships",
            "font": {
                "color": [
                    0,
                    0,
                    0,
                    255
                ],
                "name": "/CLEPKC+HelveticaNeue-LightCond",
                "size": 1
            },
            "text_vi": "Đóng góp cho quan hệ đối tác"
        },
        {
            "bbox": [
                764.6013168067227,
                670.15510391924,
                31.628536974789995,
                9.209186757719692
            ],
            "text": "2,491",
            "font": {
                "color": [
                    0,
                    0,
                    0,
                    255
                ],
                "name": "/CLFAHM+HelveticaNeue-MediumCond",
                "size": 1
            },
            "text_vi": "2.491"
        },
        {
            "bbox": [
                858.604049579832,
                670.15510391924,
                31.628554201680686,
                9.209186757719692
            ],
            "text": "5,275",
            "font": {
                "color": [
                    0,
                    0,
                    0,
                    255
                ],
                "name": "/CLEPKC+HelveticaNeue-LightCond",
                "size": 1
            },
            "text_vi": "5.275"
        },
        {
            "bbox": [
                143.09844462184876,
                685.3717402019003,
                365.1884608403361,
                9.209174584323023
            ],
            "text": "Interest in partnership acquired through acquisition of controlled entity",
            "font": {
                "color": [
                    0,
                    0,
                    0,
                    255
                ],
                "name": "/CLEPKC+HelveticaNeue-LightCond",
                "size": 1
            },
            "text_vi": "Quan tâm đến quan hệ đối tác có được thông qua việc mua lại thực thể có kiểm soát"
        },
        {
            "bbox": [
                791.0770840336135,
                685.3717402019003,
                5.154302941176525,
                9.209174584323023
            ],
            "text": "-",
            "font": {
                "color": [
                    0,
                    0,
                    0,
                    255
                ],
                "name": "/CLFAHM+HelveticaNeue-MediumCond",
                "size": 1
            },
            "text_vi": "-"
        },
        {
            "bbox": [
                851.5754953781512,
                685.3717402019003,
                38.65710840336146,
                9.209174584323023
            ],
            "text": "61,572",
            "font": {
                "color": [
                    0,
                    0,
                    0,
                    255
                ],
                "name": "/CLEPKC+HelveticaNeue-LightCond",
                "size": 1
            },
            "text_vi": "61,572"
        },
        {
            "bbox": [
                143.09844462184876,
                700.5885956057007,
                152.5331751260504,
                9.209186757719692
            ],
            "text": "Share of joint venture entities",
            "font": {
                "color": [
                    0,
                    0,
                    0,
                    255
                ],
                "name": "/CLEPKC+HelveticaNeue-LightCond",
                "size": 1
            },
            "text_vi": "Chia sẻ của các thực thể liên doanh"
        },
        {
            "bbox": [
                295.61947478991596,
                700.5926128266033,
                3.514268487394986,
                4.604550771971503
            ],
            "text": "2",
            "font": {
                "color": [
                    0,
                    0,
                    0,
                    255
                ],
                "name": "/CLEPKC+HelveticaNeue-LightCond",
                "size": 1
            },
            "text_vi": "2"
        },
        {
            "bbox": [
                302.99931974789916,
                700.5885956057007,
                46.68142857142857,
                9.209186757719692
            ],
            "text": "net profit",
            "font": {
                "color": [
                    0,
                    0,
                    0,
                    255
                ],
                "name": "/CLEPKC+HelveticaNeue-LightCond",
                "size": 1
            },
            "text_vi": "lợi nhuận ròng"
        },
        {
            "bbox": [
                764.6007827731092,
                700.5885956057007,
                31.628554201680686,
                9.209186757719692
            ],
            "text": "5,447",
            "font": {
                "color": [
                    0,
                    0,
                    0,
                    255
                ],
                "name": "/CLFAHM+HelveticaNeue-MediumCond",
                "size": 1
            },
            "text_vi": "5.447"
        },
        {
            "bbox": [
                858.6035155462185,
                700.5885956057007,
                31.628554201680686,
                9.209186757719692
            ],
            "text": "5,719",
            "font": {
                "color": [
                    0,
                    0,
                    0,
                    255
                ],
                "name": "/CLEPKC+HelveticaNeue-LightCond",
                "size": 1
            },
            "text_vi": "5.719"
        },
        {
            "bbox": [
                143.09844462184876,
                715.8053414489311,
                231.13310369747902,
                9.209186757719749
            ],
            "text": "Drawings/distributions from the partnerships",
            "font": {
                "color": [
                    0,
                    0,
                    0,
                    255
                ],
                "name": "/CLEPKC+HelveticaNeue-LightCond",
                "size": 1
            },
            "text_vi": "Bản vẽ/phân phối từ các quan hệ đối tác"
        },
        {
            "bbox": [
                753.7831911764707,
                715.8053414489311,
                46.23044579831924,
                9.209186757719749
            ],
            "text": "(14,526)",
            "font": {
                "color": [
                    0,
                    0,
                    0,
                    255
                ],
                "name": "/CLFAHM+HelveticaNeue-MediumCond",
                "size": 1
            },
            "text_vi": "(14,526)"
        },
        {
            "bbox": [
                848.3247983193278,
                715.8053414489311,
                45.15855420168077,
                9.209186757719749
            ],
            "text": "(11,754)",
            "font": {
                "color": [
                    0,
                    0,
                    0,
                    255
                ],
                "name": "/CLEPKC+HelveticaNeue-LightCond",
                "size": 1
            },
            "text_vi": "(11.754)"
        },
        {
            "bbox": [
                143.09844462184876,
                731.0220872921616,
                80.85199655462182,
                9.209186757719749
            ],
            "text": "Other expenses",
            "font": {
                "color": [
                    0,
                    0,
                    0,
                    255
                ],
                "name": "/CLEPKC+HelveticaNeue-LightCond",
                "size": 1
            },
            "text_vi": "Chi phí khác"
        },
        {
            "bbox": [
                775.1427441176471,
                731.0220872921616,
                21.085697058823484,
                9.209186757719749
            ],
            "text": "504",
            "font": {
                "color": [
                    0,
                    0,
                    0,
                    255
                ],
                "name": "/CLFAHM+HelveticaNeue-MediumCond",
                "size": 1
            },
            "text_vi": "504"
        },
        {
            "bbox": [
                869.144012605042,
                731.0220872921616,
                21.085748739495784,
                9.209186757719749
            ],
            "text": "134",
            "font": {
                "color": [
                    0,
                    0,
                    0,
                    255
                ],
                "name": "/CLEPKC+HelveticaNeue-LightCond",
                "size": 1
            },
            "text_vi": "134"
        },
        {
            "bbox": [
                143.09844462184876,
                753.1402969121141,
                271.4975864705882,
                9.209174584323023
            ],
            "text": "Carrying amount at the end of the financial year",
            "font": {
                "color": [
                    0,
                    0,
                    0,
                    255
                ],
                "name": "/CLFAHM+HelveticaNeue-MediumCond",
                "size": 1
            },
            "text_vi": "Mang theo số tiền vào cuối năm tài chính"
        },
        {
            "bbox": [
                688.1700126050421,
                753.1402969121141,
                14.057160084033626,
                9.209174584323023
            ],
            "text": "16",
            "font": {
                "color": [
                    0,
                    0,
                    0,
                    255
                ],
                "name": "/CLEPKC+HelveticaNeue-LightCond",
                "size": 1
            },
            "text_vi": "16"
        },
        {
            "bbox": [
                757.572762605042,
                753.1402969121141,
                38.657142857142844,
                9.209174584323023
            ],
            "text": "68,514",
            "font": {
                "color": [
                    0,
                    0,
                    0,
                    255
                ],
                "name": "/CLFAHM+HelveticaNeue-MediumCond",
                "size": 1
            },
            "text_vi": "68,514"
        },
        {
            "bbox": [
                851.574031092437,
                753.1402969121141,
                38.65709117647066,
                9.209174584323023
            ],
            "text": "74,598",
            "font": {
                "color": [
                    0,
                    0,
                    0,
                    255
                ],
                "name": "/CLEPKC+HelveticaNeue-LightCond",
                "size": 1
            },
            "text_vi": "74.598"
        },
        {
            "bbox": [
                125.51891252100842,
                992.1978075712589,
                10.747342058823534,
                7.042309976247033
            ],
            "text": "75",
            "font": {
                "color": [
                    0,
                    0,
                    0,
                    255
                ],
                "name": "/CLEPKB+HelveticaNeue-BoldCond",
                "size": 1
            },
            "text_vi": "75"
        },
        {
            "bbox": [
                143.09844462184876,
                331.31365944180527,
                408.2706751260504,
                9.209101543943007
            ],
            "text": "The consolidated entity’s share of the joint venture entities’ results consists of:",
            "font": {
                "color": [
                    0,
                    0,
                    0,
                    255
                ],
                "name": "/CLEPKC+HelveticaNeue-LightCond",
                "size": 1
            },
            "text_vi": "Các thực thể hợp nhất chia sẻ kết quả của các thực thể liên doanh bao gồm:"
        },
        {
            "bbox": [
                143.09844462184876,
                429.5147948337293,
                99.28151378151261,
                9.209174584323023
            ],
            "text": "Non-current assets",
            "font": {
                "color": [
                    0,
                    0,
                    0,
                    255
                ],
                "name": "/CLEPKC+HelveticaNeue-LightCond",
                "size": 1
            },
            "text_vi": "Tài sản phi hiện tại"
        },
        {
            "bbox": [
                757.572762605042,
                527.7167458432305,
                38.657142857142844,
                9.20917458432308
            ],
            "text": "68,514",
            "font": {
                "color": [
                    0,
                    0,
                    0,
                    255
                ],
                "name": "/CLFAHM+HelveticaNeue-MediumCond",
                "size": 1
            },
            "text_vi": "68,514"
        },
        {
            "bbox": [
                143.09844462184876,
                617.60339043943,
                401.3577822689076,
                9.209174584323023
            ],
            "text": "Share of joint venture entities’ retained profits at the end of the financial year",
            "font": {
                "color": [
                    0,
                    0,
                    0,
                    255
                ],
                "name": "/CLEPKC+HelveticaNeue-LightCond",
                "size": 1
            },
            "text_vi": "Chia sẻ của các thực thể liên doanh, người giữ lại lợi nhuận vào cuối năm tài chính"
        },
        {
            "bbox": [
                295.61947478991596,
                700.5926128266033,
                1.7571428571429237,
                4.604550771971503
            ],
            "text": "’",
            "font": {
                "color": [
                    0,
                    0,
                    0,
                    255
                ],
                "name": "/CLEPKC+HelveticaNeue-LightCond",
                "size": 1
            },
            "text_vi": "\""
        },
        {
            "bbox": [
                143.09837915966386,
                775.2588717339668,
                580.8118674789916,
                9.209174584323023
            ],
            "text": "Elizabeth City Centre Pty Limited acts as the agent for the Elizabeth City Centre Partnership and does not trade ",
            "font": {
                "color": [
                    0,
                    0,
                    0,
                    255
                ],
                "name": "/CLEPKC+HelveticaNeue-LightCond",
                "size": 1
            },
            "text_vi": "Trung tâm thành phố Elizabeth Pty Limited đóng vai trò là đại lý cho quan hệ đối tác của Trung tâm Thành phố Elizabeth và không giao dịch "
        },
        {
            "bbox": [
                143.09837915966386,
                790.4757514845605,
                581.9012615966387,
                9.209174584323051
            ],
            "text": "in its own right. As agent, it records the liabilities with a corresponding right of indemnity over the assets of the ",
            "font": {
                "color": [
                    0,
                    0,
                    0,
                    255
                ],
                "name": "/CLEPKC+HelveticaNeue-LightCond",
                "size": 1
            },
            "text_vi": "theo đúng nghĩa của nó. Là đại lý, nó ghi lại các khoản nợ với quyền bồi thường tương ứng đối với tài sản của "
        },
        {
            "bbox": [
                143.09837915966386,
                805.6926312351544,
                566.0196531932773,
                9.20917458432308
            ],
            "text": "partnership. The investment in Elizabeth City Centre Pty Limited is valued at the lower of cost, which is 50% ",
            "font": {
                "color": [
                    0,
                    0,
                    0,
                    255
                ],
                "name": "/CLEPKC+HelveticaNeue-LightCond",
                "size": 1
            },
            "text_vi": "quan hệ đối tác. Đầu tư vào Trung tâm thành phố Elizabeth Pty Limited có giá trị thấp hơn chi phí, là 50% "
        },
        {
            "bbox": [
                143.09837915966386,
                820.9094988123516,
                351.83127756302525,
                9.209174584323051
            ],
            "text": "of the net tangible assets of the company, and recoverable amount.",
            "font": {
                "color": [
                    0,
                    0,
                    0,
                    255
                ],
                "name": "/CLEPKC+HelveticaNeue-LightCond",
                "size": 1
            },
            "text_vi": "tài sản hữu hình ròng của công ty và số tiền có thể thu hồi được."
        },
        {
            "bbox": [
                121.12398642857144,
                89.08305433491682,
                475.2080589495798,
                10.292619061757705
            ],
            "text": "NOTES TO AND FORMING PART OF THE FINANCIAL STATEMENTS",
            "font": {
                "color": [
                    0,
                    0,
                    0,
                    255
                ],
                "name": "/CLEPLD+HelveticaNeue-Condensed",
                "size": 1
            },
            "text_vi": "Ghi chú và hình thành một phần của báo cáo tài chính"
        },
        {
            "bbox": [
                121.12398642857144,
                103.42965795724467,
                173.35511987394958,
                8.342465261282655
            ],
            "text": "For the year ended 30 June 2002",
            "font": {
                "color": [
                    0,
                    0,
                    0,
                    255
                ],
                "name": "/CLEPKB+HelveticaNeue-BoldCond",
                "size": 1
            },
            "text_vi": "Cho năm kết thúc vào ngày 30 tháng 6 năm 2002"
        },
        {
            "bbox": [
                297.9995592436975,
                103.42965795724467,
                399.63637142857147,
                8.342465261282655
            ],
            "text": "Stockland Trust Group comprising Stockland Trust and Stockland Corporation Limited",
            "font": {
                "color": [
                    0,
                    0,
                    0,
                    255
                ],
                "name": "/CLEPKC+HelveticaNeue-LightCond",
                "size": 1
            },
            "text_vi": "Stockland Trust Group bao gồm Stockland Trust và Stockland Corporation Limited"
        },
        {
            "bbox": [
                538.5322264705882,
                166.26672298099766,
                49.04039285714293,
                9.209101543943007
            ],
            "text": "Principal",
            "font": {
                "color": [
                    0,
                    0,
                    0,
                    255
                ],
                "name": "/CLFAHM+HelveticaNeue-MediumCond",
                "size": 1
            },
            "text_vi": "Hiệu trưởng"
        },
        {
            "bbox": [
                687.0546920168067,
                166.26672298099766,
                44.98728445378151,
                9.209101543943007
            ],
            "text": "Balance",
            "font": {
                "color": [
                    0,
                    0,
                    0,
                    255
                ],
                "name": "/CLFAHM+HelveticaNeue-MediumCond",
                "size": 1
            },
            "text_vi": "Sự cân bằng"
        },
        {
            "bbox": [
                825.9612794117647,
                166.26672298099766,
                60.16899873949592,
                9.209101543943007
            ],
            "text": "Ownership",
            "font": {
                "color": [
                    0,
                    0,
                    0,
                    255
                ],
                "name": "/CLFAHM+HelveticaNeue-MediumCond",
                "size": 1
            },
            "text_vi": "Quyền sở hữu"
        },
        {
            "bbox": [
                542.8636008403362,
                179.0488625296913,
                40.37621428571424,
                9.209101543942893
            ],
            "text": "activity",
            "font": {
                "color": [
                    0,
                    0,
                    0,
                    255
                ],
                "name": "/CLFAHM+HelveticaNeue-MediumCond",
                "size": 1
            },
            "text_vi": "hoạt động "
        },
        {
            "bbox": [
                697.2139752100841,
                179.0488625296913,
                24.661517226890737,
                9.209101543942893
            ],
            "text": "date",
            "font": {
                "color": [
                    0,
                    0,
                    0,
                    255
                ],
                "name": "/CLFAHM+HelveticaNeue-MediumCond",
                "size": 1
            },
            "text_vi": "ngày"
        },
        {
            "bbox": [
                834.6679394957984,
                179.0488625296913,
                42.73807268907558,
                9.209101543942893
            ],
            "text": "interest",
            "font": {
                "color": [
                    0,
                    0,
                    0,
                    255
                ],
                "name": "/CLFAHM+HelveticaNeue-MediumCond",
                "size": 1
            },
            "text_vi": "quan tâm"
        },
        {
            "bbox": [
                790.4290256302521,
                265.46288747030883,
                72.64030294117651,
                9.209113717339733
            ],
            "text": "Consolidated",
            "font": {
                "color": [
                    0,
                    0,
                    0,
                    255
                ],
                "name": "/CLFAHM+HelveticaNeue-MediumCond",
                "size": 1
            },
            "text_vi": "Hợp nhất"
        },
        {
            "bbox": [
                676.1972029411764,
                278.2450391923991,
                26.029125630252224,
                9.209101543943007
            ],
            "text": "Note",
            "font": {
                "color": [
                    0,
                    0,
                    0,
                    255
                ],
                "name": "/CLFAHM+HelveticaNeue-MediumCond",
                "size": 1
            },
            "text_vi": "Ghi chú"
        },
        {
            "bbox": [
                768.1162399159665,
                278.2450391923991,
                28.10841134453767,
                9.209101543943007
            ],
            "text": "2002",
            "font": {
                "color": [
                    0,
                    0,
                    0,
                    255
                ],
                "name": "/CLFAHM+HelveticaNeue-MediumCond",
                "size": 1
            },
            "text_vi": "2002"
        },
        {
            "bbox": [
                862.1160957983194,
                278.2450391923991,
                28.114285714285643,
                9.209101543943007
            ],
            "text": "2001",
            "font": {
                "color": [
                    0,
                    0,
                    0,
                    255
                ],
                "name": "/CLEPKC+HelveticaNeue-LightCond",
                "size": 1
            },
            "text_vi": "2001"
        },
        {
            "bbox": [
                764.6005243697479,
                291.0271787410926,
                31.62858865546218,
                9.209101543943007
            ],
            "text": "$’000",
            "font": {
                "color": [
                    0,
                    0,
                    0,
                    255
                ],
                "name": "/CLFAHM+HelveticaNeue-MediumCond",
                "size": 1
            },
            "text_vi": "$ 000 000"
        },
        {
            "bbox": [
                858.6032571428573,
                291.0271787410926,
                31.628605882352872,
                9.209101543943007
            ],
            "text": "$’000",
            "font": {
                "color": [
                    0,
                    0,
                    0,
                    255
                ],
                "name": "/CLEPKC+HelveticaNeue-LightCond",
                "size": 1
            },
            "text_vi": "$ 000 000"
        }
    ]
}