{
    "metadata": {
        "page_hash": "a64d028ace41e7b53db8d0009e6ae9d31617ad4437f9a06ec8c276293f9d5150",
        "original_filename": "DE-05-Abwassersammelstation-LV.pdf",
        "page_no": 31,
        "num_pages": 102,
        "original_width": 595.32001,
        "original_height": 841.91998,
        "coco_width": 1025,
        "coco_height": 1025,
        "collection": "eu_tenders",
        "doc_category": "government_tenders"
    },
    "cells": [
        {
            "bbox": [
                131.85950191729654,
                86.47335908336561,
                165.90220106997577,
                16.172677123068183
            ],
            "text": "Anschlussgewinde: ",
            "font": {
                "color": [
                    0,
                    0,
                    0,
                    255
                ],
                "name": "/Times New Roman",
                "size": 12
            },
            "text_vi": "Chủ đề kết nối: "
        },
        {
            "bbox": [
                379.83814788956954,
                86.47335908336561,
                44.83469277305153,
                16.172677123068183
            ],
            "text": "G 1“ ",
            "font": {
                "color": [
                    0,
                    0,
                    0,
                    255
                ],
                "name": "/Times New Roman",
                "size": 12
            },
            "text_vi": "G 1 \" "
        },
        {
            "bbox": [
                180.6129446245222,
                144.4973306726846,
                51.65287447670369,
                16.172664948514466
            ],
            "text": "7.1.7. ",
            "font": {
                "color": [
                    0,
                    0,
                    0,
                    255
                ],
                "name": "/Times New Roman,Bold",
                "size": 12
            },
            "text_vi": "7.1.7. "
        },
        {
            "bbox": [
                255.8195549314729,
                144.4973306726846,
                300.70593503147995,
                16.172664948514466
            ],
            "text": "Behälterreinigungskopf X03, X04 ",
            "font": {
                "color": [
                    0,
                    0,
                    0,
                    255
                ],
                "name": "/Times New Roman,Bold",
                "size": 12
            },
            "text_vi": "Đầu vệ sinh container x03, x04 "
        },
        {
            "bbox": [
                131.85950191729654,
                185.40379455064124,
                93.58815269790779,
                16.172677123068183
            ],
            "text": "Funktion: ",
            "font": {
                "color": [
                    0,
                    0,
                    0,
                    255
                ],
                "name": "/Times New Roman,Bold",
                "size": 12
            },
            "text_vi": "Chức năng: "
        },
        {
            "bbox": [
                131.85950191729654,
                218.71336127454776,
                34.7107363315404,
                16.172664948514466
            ],
            "text": "Zur ",
            "font": {
                "color": [
                    0,
                    0,
                    0,
                    255
                ],
                "name": "/Times New Roman",
                "size": 12
            },
            "text_vi": "ĐẾN "
        },
        {
            "bbox": [
                187.00412909016782,
                218.71336127454776,
                242.4380296741579,
                16.172664948514466
            ],
            "text": "Behälterinnenraumreinigung ",
            "font": {
                "color": [
                    0,
                    0,
                    0,
                    255
                ],
                "name": "/Times New Roman",
                "size": 12
            },
            "text_vi": "Làm sạch container "
        },
        {
            "bbox": [
                449.6694139341965,
                218.71336127454776,
                32.70661102085245,
                16.172664948514466
            ],
            "text": "vor ",
            "font": {
                "color": [
                    0,
                    0,
                    0,
                    255
                ],
                "name": "/Times New Roman",
                "size": 12
            },
            "text_vi": "trước "
        },
        {
            "bbox": [
                502.74792543929436,
                218.71336127454776,
                107.496537450505,
                16.172664948514466
            ],
            "text": "Inspektions- ",
            "font": {
                "color": [
                    0,
                    0,
                    0,
                    255
                ],
                "name": "/Times New Roman",
                "size": 12
            },
            "text_vi": "Điều tra "
        },
        {
            "bbox": [
                630.492413651609,
                218.71336127454776,
                41.79751995905531,
                16.172664948514466
            ],
            "text": "oder ",
            "font": {
                "color": [
                    0,
                    0,
                    0,
                    255
                ],
                "name": "/Times New Roman",
                "size": 12
            },
            "text_vi": "hoặc "
        },
        {
            "bbox": [
                692.4552397457629,
                218.71336127454776,
                153.0164919200347,
                16.172664948514466
            ],
            "text": "Reparaturarbeiten ",
            "font": {
                "color": [
                    0,
                    0,
                    0,
                    255
                ],
                "name": "/Times New Roman",
                "size": 12
            },
            "text_vi": "Công việc sửa chữa "
        },
        {
            "bbox": [
                865.6989696180378,
                218.71336127454776,
                32.62396639414169,
                16.172664948514466
            ],
            "text": "mit ",
            "font": {
                "color": [
                    0,
                    0,
                    0,
                    255
                ],
                "name": "/Times New Roman",
                "size": 12
            },
            "text_vi": "với "
        },
        {
            "bbox": [
                131.85950191729654,
                235.51422101896196,
                135.1033035157007,
                16.17267712306807
            ],
            "text": "Betriebswasser. ",
            "font": {
                "color": [
                    0,
                    0,
                    0,
                    255
                ],
                "name": "/Times New Roman",
                "size": 12
            },
            "text_vi": "Nước hoạt động. "
        },
        {
            "bbox": [
                288.84298757234785,
                235.51422101896196,
                25.826445847167122,
                16.17267712306807
            ],
            "text": "Es ",
            "font": {
                "color": [
                    0,
                    0,
                    0,
                    255
                ],
                "name": "/Times New Roman",
                "size": 12
            },
            "text_vi": "Nó "
        },
        {
            "bbox": [
                336.7562099080123,
                235.51422101896196,
                63.78097344653344,
                16.17267712306807
            ],
            "text": "kommt ",
            "font": {
                "color": [
                    0,
                    0,
                    0,
                    255
                ],
                "name": "/Times New Roman",
                "size": 12
            },
            "text_vi": "đến "
        },
        {
            "bbox": [
                422.4586705896212,
                235.51422101896196,
                30.330595220543614,
                16.17267712306807
            ],
            "text": "ein ",
            "font": {
                "color": [
                    0,
                    0,
                    0,
                    255
                ],
                "name": "/Times New Roman",
                "size": 12
            },
            "text_vi": "Một "
        },
        {
            "bbox": [
                474.7107530452403,
                235.51422101896196,
                32.78925564756338,
                16.17267712306807
            ],
            "text": "mit ",
            "font": {
                "color": [
                    0,
                    0,
                    0,
                    255
                ],
                "name": "/Times New Roman",
                "size": 12
            },
            "text_vi": "với "
        },
        {
            "bbox": [
                529.4214959278792,
                235.51422101896196,
                40.45454477500266,
                16.17267712306807
            ],
            "text": "dem ",
            "font": {
                "color": [
                    0,
                    0,
                    0,
                    255
                ],
                "name": "/Times New Roman",
                "size": 12
            },
            "text_vi": "dem "
        },
        {
            "bbox": [
                591.7975107203267,
                235.51422101896196,
                167.02479058279926,
                16.17267712306807
            ],
            "text": "Reinigungsmedium ",
            "font": {
                "color": [
                    0,
                    0,
                    0,
                    255
                ],
                "name": "/Times New Roman",
                "size": 12
            },
            "text_vi": "Phương tiện làm sạch "
        },
        {
            "bbox": [
                780.7437713205709,
                235.51422101896196,
                117.3760310862051,
                16.17267712306807
            ],
            "text": "angetriebener ",
            "font": {
                "color": [
                    0,
                    0,
                    0,
                    255
                ],
                "name": "/Times New Roman",
                "size": 12
            },
            "text_vi": "lái "
        },
        {
            "bbox": [
                131.85950191729654,
                252.31516598525184,
                280.0034560403908,
                16.172677123068183
            ],
            "text": "Düsenrotationskopf zum Einsatz. ",
            "font": {
                "color": [
                    0,
                    0,
                    0,
                    255
                ],
                "name": "/Times New Roman",
                "size": 12
            },
            "text_vi": "Đầu quay phản lực được sử dụng. "
        },
        {
            "bbox": [
                131.85950191729654,
                286.20908693721697,
                118.79476384474296,
                16.17267712306807
            ],
            "text": "Ausführung: ",
            "font": {
                "color": [
                    0,
                    0,
                    0,
                    255
                ],
                "name": "/Times New Roman,Bold",
                "size": 12
            },
            "text_vi": "Thực thi: "
        },
        {
            "bbox": [
                131.85950191729654,
                302.7177817421556,
                79.38961643503299,
                16.172664948514466
            ],
            "text": "Hersteller:",
            "font": {
                "color": [
                    0,
                    0,
                    0,
                    255
                ],
                "name": "/Times New Roman",
                "size": 12
            },
            "text_vi": "Nhà sản xuất:"
        },
        {
            "bbox": [
                327.1005454696542,
                302.7177817421556,
                229.01168692448277,
                16.172664948514466
            ],
            "text": "Lechler, oder gleichwertig. ",
            "font": {
                "color": [
                    0,
                    0,
                    0,
                    255
                ],
                "name": "/Times New Roman",
                "size": 12
            },
            "text_vi": "Lechler, hoặc tương đương. "
        },
        {
            "bbox": [
                131.85950191729654,
                319.5186414865698,
                33.78171775210444,
                16.172677123068183
            ],
            "text": "Typ:",
            "font": {
                "color": [
                    0,
                    0,
                    0,
                    255
                ],
                "name": "/Times New Roman",
                "size": 12
            },
            "text_vi": "Kiểu:"
        },
        {
            "bbox": [
                327.1005454696542,
                319.5186414865698,
                36.208659860097725,
                16.172677123068183
            ],
            "text": "569 ",
            "font": {
                "color": [
                    0,
                    0,
                    0,
                    255
                ],
                "name": "/Times New Roman",
                "size": 12
            },
            "text_vi": "569 "
        },
        {
            "bbox": [
                131.85950191729654,
                336.35607359027165,
                79.17126244421047,
                16.17267712306807
            ],
            "text": "Werkstoff:",
            "font": {
                "color": [
                    0,
                    0,
                    0,
                    255
                ],
                "name": "/Times New Roman",
                "size": 12
            },
            "text_vi": "Vật liệu:"
        },
        {
            "bbox": [
                327.1005454696542,
                336.35607359027165,
                62.03510570726485,
                16.17267712306807
            ],
            "text": "1.4404 ",
            "font": {
                "color": [
                    0,
                    0,
                    0,
                    255
                ],
                "name": "/Times New Roman",
                "size": 12
            },
            "text_vi": "1.4404 "
        },
        {
            "bbox": [
                131.85950191729654,
                353.15694550923945,
                155.72024531814412,
                16.172677123068183
            ],
            "text": "Werkstoffbelegung:",
            "font": {
                "color": [
                    0,
                    0,
                    0,
                    255
                ],
                "name": "/Times New Roman",
                "size": 12
            },
            "text_vi": "Chiếm chỗ vật chất:"
        },
        {
            "bbox": [
                327.1005454696542,
                353.15694550923945,
                163.0681790790133,
                16.172677123068183
            ],
            "text": "DIN EN 10204/2.2 ",
            "font": {
                "color": [
                    0,
                    0,
                    0,
                    255
                ],
                "name": "/Times New Roman",
                "size": 12
            },
            "text_vi": "DIN EN 10204/2.2 "
        },
        {
            "bbox": [
                131.85950191729654,
                369.95789047552944,
                83.68367628025806,
                16.172664948514466
            ],
            "text": "Anschluss:",
            "font": {
                "color": [
                    0,
                    0,
                    0,
                    255
                ],
                "name": "/Times New Roman",
                "size": 12
            },
            "text_vi": "Sự liên quan:"
        },
        {
            "bbox": [
                327.1005454696542,
                369.95789047552944,
                60.795436306600834,
                16.172664948514466
            ],
            "text": "G 3/4“ ",
            "font": {
                "color": [
                    0,
                    0,
                    0,
                    255
                ],
                "name": "/Times New Roman",
                "size": 12
            },
            "text_vi": "G 3/4 \" "
        },
        {
            "bbox": [
                180.6129446245222,
                427.9574764338055,
                51.65287447670369,
                16.172677123068183
            ],
            "text": "7.1.8. ",
            "font": {
                "color": [
                    0,
                    0,
                    0,
                    255
                ],
                "name": "/Times New Roman,Bold",
                "size": 12
            },
            "text_vi": "7.1.8. "
        },
        {
            "bbox": [
                255.8195549314729,
                427.9574764338055,
                239.92766470255208,
                16.172677123068183
            ],
            "text": "Schlauchpumpen P01, P02 ",
            "font": {
                "color": [
                    0,
                    0,
                    0,
                    255
                ],
                "name": "/Times New Roman,Bold",
                "size": 12
            },
            "text_vi": "Máy bơm ống P01, P02 "
        },
        {
            "bbox": [
                131.85950191729654,
                468.863989009977,
                93.58815269790779,
                16.17267712306807
            ],
            "text": "Funktion: ",
            "font": {
                "color": [
                    0,
                    0,
                    0,
                    255
                ],
                "name": "/Times New Roman,Bold",
                "size": 12
            },
            "text_vi": "Chức năng: "
        },
        {
            "bbox": [
                131.85950191729654,
                485.3726838149155,
                56.61158651462094,
                16.172664948514466
            ],
            "text": "Durch ",
            "font": {
                "color": [
                    0,
                    0,
                    0,
                    255
                ],
                "name": "/Times New Roman",
                "size": 12
            },
            "text_vi": "Bởi vì "
        },
        {
            "bbox": [
                205.39259296861195,
                485.3726838149155,
                30.557833508737588,
                16.172664948514466
            ],
            "text": "die ",
            "font": {
                "color": [
                    0,
                    0,
                    0,
                    255
                ],
                "name": "/Times New Roman",
                "size": 12
            },
            "text_vi": "các "
        },
        {
            "bbox": [
                252.87191379641345,
                485.3726838149155,
                137.1900631225213,
                16.172664948514466
            ],
            "text": "Schlauchpumpe ",
            "font": {
                "color": [
                    0,
                    0,
                    0,
                    255
                ],
                "name": "/Times New Roman",
                "size": 12
            },
            "text_vi": "Máy bơm vòi "
        },
        {
            "bbox": [
                406.94215914227374,
                485.3726838149155,
                60.061948026910784,
                16.172664948514466
            ],
            "text": "erfolgt ",
            "font": {
                "color": [
                    0,
                    0,
                    0,
                    255
                ],
                "name": "/Times New Roman",
                "size": 12
            },
            "text_vi": "diễn ra "
        },
        {
            "bbox": [
                483.9668995839734,
                485.3726838149155,
                30.5578851616292,
                16.172664948514466
            ],
            "text": "die ",
            "font": {
                "color": [
                    0,
                    0,
                    0,
                    255
                ],
                "name": "/Times New Roman",
                "size": 12
            },
            "text_vi": "các "
        },
        {
            "bbox": [
                531.4462720646665,
                485.3726838149155,
                80.76444423563066,
                16.172664948514466
            ],
            "text": "Speisung ",
            "font": {
                "color": [
                    0,
                    0,
                    0,
                    255
                ],
                "name": "/Times New Roman",
                "size": 12
            },
            "text_vi": "Cho ăn "
        },
        {
            "bbox": [
                629.1322036193609,
                485.3726838149155,
                31.652909247918615,
                16.172664948514466
            ],
            "text": "der ",
            "font": {
                "color": [
                    0,
                    0,
                    0,
                    255
                ],
                "name": "/Times New Roman",
                "size": 12
            },
            "text_vi": "các "
        },
        {
            "bbox": [
                677.8511938478265,
                485.3726838149155,
                176.03308932955224,
                16.172664948514466
            ],
            "text": "Flüssigstrahlmischer ",
            "font": {
                "color": [
                    0,
                    0,
                    0,
                    255
                ],
                "name": "/Times New Roman",
                "size": 12
            },
            "text_vi": "Máy trộn nổ chất lỏng "
        },
        {
            "bbox": [
                870.7437870264096,
                485.3726838149155,
                27.252117310822314,
                16.172664948514466
            ],
            "text": "im ",
            "font": {
                "color": [
                    0,
                    0,
                    0,
                    255
                ],
                "name": "/Times New Roman",
                "size": 12
            },
            "text_vi": "trong "
        },
        {
            "bbox": [
                131.85950191729654,
                502.1735435593297,
                146.80054849827746,
                16.172677123068183
            ],
            "text": "Behälterinnenraum",
            "font": {
                "color": [
                    0,
                    0,
                    0,
                    255
                ],
                "name": "/Times New Roman",
                "size": 12
            },
            "text_vi": "Container"
        },
        {
            "bbox": [
                299.222687811216,
                502.1735435593297,
                156.22510068156458,
                16.172677123068183
            ],
            "text": "zur Vermeidung der",
            "font": {
                "color": [
                    0,
                    0,
                    0,
                    255
                ],
                "name": "/Times New Roman",
                "size": 12
            },
            "text_vi": "Để tránh"
        },
        {
            "bbox": [
                476.01047754131423,
                502.1735435593297,
                183.25915670128416,
                16.172677123068183
            ],
            "text": "Abwasserentmischung,",
            "font": {
                "color": [
                    0,
                    0,
                    0,
                    255
                ],
                "name": "/Times New Roman",
                "size": 12
            },
            "text_vi": "Trang trí nước thải,"
        },
        {
            "bbox": [
                679.8322716382404,
                502.1735435593297,
                156.09751803907955,
                16.172677123068183
            ],
            "text": "Sedimentierung und",
            "font": {
                "color": [
                    0,
                    0,
                    0,
                    255
                ],
                "name": "/Times New Roman",
                "size": 12
            },
            "text_vi": "Trầm tích và"
        },
        {
            "bbox": [
                856.492427072962,
                502.1735435593297,
                41.672141173282625,
                16.172677123068183
            ],
            "text": "zum ",
            "font": {
                "color": [
                    0,
                    0,
                    0,
                    255
                ],
                "name": "/Times New Roman",
                "size": 12
            },
            "text_vi": "cho "
        },
        {
            "bbox": [
                131.85950191729654,
                518.9744154782976,
                590.3684473834501,
                16.172677123068127
            ],
            "text": "Betreiben der Behälter. Sie sind in redundanter Ausführung eingesetzt. ",
            "font": {
                "color": [
                    0,
                    0,
                    0,
                    255
                ],
                "name": "/Times New Roman",
                "size": 12
            },
            "text_vi": "Vận hành các container. Chúng được sử dụng trong một thực thi dự phòng. "
        },
        {
            "bbox": [
                131.85950191729654,
                552.5761958398944,
                192.04892928090896,
                16.172664948514466
            ],
            "text": "Die einzusetzende Pumpe",
            "font": {
                "color": [
                    0,
                    0,
                    0,
                    255
                ],
                "name": "/Times New Roman",
                "size": 12
            },
            "text_vi": "Máy bơm sẽ được sử dụng"
        },
        {
            "bbox": [
                343.7773874760232,
                552.5761958398944,
                61.79102857637855,
                16.172664948514466
            ],
            "text": "ist über",
            "font": {
                "color": [
                    0,
                    0,
                    0,
                    255
                ],
                "name": "/Times New Roman",
                "size": 12
            },
            "text_vi": "Là kết thúc"
        },
        {
            "bbox": [
                425.43738954785005,
                552.5761958398944,
                114.45786653467263,
                16.172664948514466
            ],
            "text": "Rohrleitungen,",
            "font": {
                "color": [
                    0,
                    0,
                    0,
                    255
                ],
                "name": "/Times New Roman",
                "size": 12
            },
            "text_vi": "Đường ống,"
        },
        {
            "bbox": [
                559.7641951427098,
                552.5761958398944,
                21.524672503449096,
                16.172664948514466
            ],
            "text": "die",
            "font": {
                "color": [
                    0,
                    0,
                    0,
                    255
                ],
                "name": "/Times New Roman",
                "size": 12
            },
            "text_vi": "các"
        },
        {
            "bbox": [
                601.1578239239766,
                552.5761958398944,
                23.497537484083637,
                16.172664948514466
            ],
            "text": "mit",
            "font": {
                "color": [
                    0,
                    0,
                    0,
                    255
                ],
                "name": "/Times New Roman",
                "size": 12
            },
            "text_vi": "với"
        },
        {
            "bbox": [
                644.5243004682472,
                552.5761958398944,
                147.73129917134827,
                16.172664948514466
            ],
            "text": "E-motorbetriebenen",
            "font": {
                "color": [
                    0,
                    0,
                    0,
                    255
                ],
                "name": "/Times New Roman",
                "size": 12
            },
            "text_vi": "Động cơ điện tử hoạt động"
        },
        {
            "bbox": [
                812.1245559174132,
                552.5761958398944,
                86.23968519049106,
                16.172664948514466
            ],
            "text": "Armaturen ",
            "font": {
                "color": [
                    0,
                    0,
                    0,
                    255
                ],
                "name": "/Times New Roman",
                "size": 12
            },
            "text_vi": "Phụ kiện "
        },
        {
            "bbox": [
                131.85950191729654,
                569.4014412153516,
                580.6576865272848,
                16.17266494851441
            ],
            "text": "saug- als auch druckseitig ausgestattet sind, ferngesteuert anzufahren. ",
            "font": {
                "color": [
                    0,
                    0,
                    0,
                    255
                ],
                "name": "/Times New Roman",
                "size": 12
            },
            "text_vi": "Hút cũng như áp lực lên áp lực để xua đuổi đi kiểm soát. "
        },
        {
            "bbox": [
                131.85950191729654,
                586.2023009597658,
                34.917365115948314,
                16.17267712306824
            ],
            "text": "Die ",
            "font": {
                "color": [
                    0,
                    0,
                    0,
                    255
                ],
                "name": "/Times New Roman",
                "size": 12
            },
            "text_vi": "Các "
        },
        {
            "bbox": [
                195.06199741211455,
                586.2023009597658,
                240.41321910210948,
                16.17267712306824
            ],
            "text": "Schlauchpumpeneinbindung ",
            "font": {
                "color": [
                    0,
                    0,
                    0,
                    255
                ],
                "name": "/Times New Roman",
                "size": 12
            },
            "text_vi": "Tích hợp bơm vòi "
        },
        {
            "bbox": [
                463.760357223672,
                586.2023009597658,
                21.466924570534843,
                16.17267712306824
            ],
            "text": "in ",
            "font": {
                "color": [
                    0,
                    0,
                    0,
                    255
                ],
                "name": "/Times New Roman",
                "size": 12
            },
            "text_vi": "TRONG "
        },
        {
            "bbox": [
                513.5124225036548,
                586.2023009597658,
                30.557867943998758,
                16.17267712306824
            ],
            "text": "die ",
            "font": {
                "color": [
                    0,
                    0,
                    0,
                    255
                ],
                "name": "/Times New Roman",
                "size": 12
            },
            "text_vi": "các "
        },
        {
            "bbox": [
                572.3554311571015,
                586.2023009597658,
                123.30578305271479,
                16.17267712306824
            ],
            "text": "Rohrleitungen ",
            "font": {
                "color": [
                    0,
                    0,
                    0,
                    255
                ],
                "name": "/Times New Roman",
                "size": 12
            },
            "text_vi": "Ống "
        },
        {
            "bbox": [
                723.9463549192643,
                586.2023009597658,
                60.247932872271576,
                16.17267712306824
            ],
            "text": "erfolgt ",
            "font": {
                "color": [
                    0,
                    0,
                    0,
                    255
                ],
                "name": "/Times New Roman",
                "size": 12
            },
            "text_vi": "diễn ra "
        },
        {
            "bbox": [
                812.5207335967087,
                586.2023009597658,
                85.49586633246201,
                16.17267712306824
            ],
            "text": "beidseitig ",
            "font": {
                "color": [
                    0,
                    0,
                    0,
                    255
                ],
                "name": "/Times New Roman",
                "size": 12
            },
            "text_vi": "cả hai bên "
        },
        {
            "bbox": [
                131.85950191729654,
                603.0032094023948,
                383.30920499379823,
                16.172677123068183
            ],
            "text": "schwingungsentkoppelt über Kompensatoren. ",
            "font": {
                "color": [
                    0,
                    0,
                    0,
                    255
                ],
                "name": "/Times New Roman",
                "size": 12
            },
            "text_vi": "Rung động trêu chọc thông qua các bộ bù. "
        },
        {
            "bbox": [
                131.85950191729654,
                636.6049897639916,
                152.0502901456311,
                16.172664948514466
            ],
            "text": "Die Schlauchpumpe",
            "font": {
                "color": [
                    0,
                    0,
                    0,
                    255
                ],
                "name": "/Times New Roman",
                "size": 12
            },
            "text_vi": "Máy bơm ống"
        },
        {
            "bbox": [
                303.6875465516437,
                636.6049897639916,
                23.389669028595222,
                16.172664948514466
            ],
            "text": "mit",
            "font": {
                "color": [
                    0,
                    0,
                    0,
                    255
                ],
                "name": "/Times New Roman",
                "size": 12
            },
            "text_vi": "với"
        },
        {
            "bbox": [
                346.85493563369386,
                636.6049897639916,
                22.390254444832124,
                16.172664948514466
            ],
            "text": "der",
            "font": {
                "color": [
                    0,
                    0,
                    0,
                    255
                ],
                "name": "/Times New Roman",
                "size": 12
            },
            "text_vi": "các"
        },
        {
            "bbox": [
                389.02294456724206,
                636.6049897639916,
                114.89688167881343,
                16.172664948514466
            ],
            "text": "anschließenden",
            "font": {
                "color": [
                    0,
                    0,
                    0,
                    255
                ],
                "name": "/Times New Roman",
                "size": 12
            },
            "text_vi": "tiếp theo"
        },
        {
            "bbox": [
                523.6975462995105,
                636.6049897639916,
                127.73135116019364,
                16.172664948514466
            ],
            "text": "Rohrleitung und",
            "font": {
                "color": [
                    0,
                    0,
                    0,
                    255
                ],
                "name": "/Times New Roman",
                "size": 12
            },
            "text_vi": "Đường ống và"
        },
        {
            "bbox": [
                671.2066863836812,
                636.6049897639916,
                25.318353569200553,
                16.172664948514466
            ],
            "text": "den",
            "font": {
                "color": [
                    0,
                    0,
                    0,
                    255
                ],
                "name": "/Times New Roman",
                "size": 12
            },
            "text_vi": "các"
        },
        {
            "bbox": [
                716.3027772239673,
                636.6049897639916,
                75.95502627234055,
                16.172664948514466
            ],
            "text": "Armaturen",
            "font": {
                "color": [
                    0,
                    0,
                    0,
                    255
                ],
                "name": "/Times New Roman",
                "size": 12
            },
            "text_vi": "Phụ kiện"
        },
        {
            "bbox": [
                812.0355407673933,
                636.6049897639916,
                86.00166866556356,
                16.172664948514466
            ],
            "text": "ist gegen ",
            "font": {
                "color": [
                    0,
                    0,
                    0,
                    255
                ],
                "name": "/Times New Roman",
                "size": 12
            },
            "text_vi": "Là chống lại "
        },
        {
            "bbox": [
                131.85950191729654,
                653.4058616829595,
                632.3105782216189,
                16.17266494851441
            ],
            "text": "unzulässig hohe Druckspitzen durch ein Druckbegrenzungsventil geschützt. ",
            "font": {
                "color": [
                    0,
                    0,
                    0,
                    255
                ],
                "name": "/Times New Roman",
                "size": 12
            },
            "text_vi": "Các mẹo áp suất cao không thể bảo vệ được bảo vệ bởi một van ranh giới áp suất. "
        },
        {
            "bbox": [
                131.85950191729654,
                670.2067214273736,
                94.38357279473945,
                16.172677123068183
            ],
            "text": "Die Pumpen",
            "font": {
                "color": [
                    0,
                    0,
                    0,
                    255
                ],
                "name": "/Times New Roman",
                "size": 12
            },
            "text_vi": "Các máy bơm"
        },
        {
            "bbox": [
                246.59959985218708,
                670.2067214273736,
                101.24128617816828,
                16.172677123068183
            ],
            "text": "druckseitigen",
            "font": {
                "color": [
                    0,
                    0,
                    0,
                    255
                ],
                "name": "/Times New Roman",
                "size": 12
            },
            "text_vi": "In bên"
        },
        {
            "bbox": [
                368.1974111705064,
                670.2067214273736,
                111.25710901268042,
                16.172677123068183
            ],
            "text": "Rohrleitungen",
            "font": {
                "color": [
                    0,
                    0,
                    0,
                    255
                ],
                "name": "/Times New Roman",
                "size": 12
            },
            "text_vi": "Ống"
        },
        {
            "bbox": [
                499.8110281057074,
                670.2067214273736,
                53.11110447975699,
                16.172677123068183
            ],
            "text": "werden",
            "font": {
                "color": [
                    0,
                    0,
                    0,
                    255
                ],
                "name": "/Times New Roman",
                "size": 12
            },
            "text_vi": "trở nên"
        },
        {
            "bbox": [
                573.278640507985,
                670.2067214273736,
                45.09838078515122,
                16.172677123068183
            ],
            "text": "durch",
            "font": {
                "color": [
                    0,
                    0,
                    0,
                    255
                ],
                "name": "/Times New Roman",
                "size": 12
            },
            "text_vi": "bởi vì"
        },
        {
            "bbox": [
                638.7335808685483,
                670.2067214273736,
                178.55278625692426,
                16.172677123068183
            ],
            "text": "Rückschlagventile vor",
            "font": {
                "color": [
                    0,
                    0,
                    0,
                    255
                ],
                "name": "/Times New Roman",
                "size": 12
            },
            "text_vi": "Van kiểm tra trước"
        },
        {
            "bbox": [
                837.6428750479931,
                670.2067214273736,
                60.311620887730555,
                16.172677123068183
            ],
            "text": "Medium ",
            "font": {
                "color": [
                    0,
                    0,
                    0,
                    255
                ],
                "name": "/Times New Roman",
                "size": 12
            },
            "text_vi": "trung bình "
        },
        {
            "bbox": [
                131.85950191729654,
                687.0076298700026,
                231.24310906330862,
                16.172677123068183
            ],
            "text": "Rückströmung abgesichert. ",
            "font": {
                "color": [
                    0,
                    0,
                    0,
                    255
                ],
                "name": "/Times New Roman",
                "size": 12
            },
            "text_vi": "Lưu lượng trở lại được bảo đảm. "
        },
        {
            "bbox": [
                131.85950191729654,
                703.9545842587083,
                113.82231213763504,
                16.172677123068127
            ],
            "text": "Ausführung:",
            "font": {
                "color": [
                    0,
                    0,
                    0,
                    255
                ],
                "name": "/Times New Roman,Bold",
                "size": 12
            },
            "text_vi": "Thực thi:"
        },
        {
            "bbox": [
                131.85950191729654,
                737.2641631571685,
                598.0130753542117,
                16.172677123068183
            ],
            "text": "Die Pumpenförderung ist mittels folgender Messstellen zu überwachen: ",
            "font": {
                "color": [
                    0,
                    0,
                    0,
                    255
                ],
                "name": "/Times New Roman",
                "size": 12
            },
            "text_vi": "Tài trợ bơm phải được theo dõi bằng các điểm đo lường sau: "
        },
        {
            "bbox": [
                131.85950191729654,
                754.0650350761364,
                11.98346915132251,
                16.172677123068127
            ],
            "text": "- ",
            "font": {
                "color": [
                    0,
                    0,
                    0,
                    255
                ],
                "name": "/Times New Roman",
                "size": 12
            },
            "text_vi": "- "
        },
        {
            "bbox": [
                193.83608489827176,
                754.0650350761364,
                107.85123785776997,
                16.172677123068127
            ],
            "text": "Durchfluss-, ",
            "font": {
                "color": [
                    0,
                    0,
                    0,
                    255
                ],
                "name": "/Times New Roman",
                "size": 12
            },
            "text_vi": "Lưu lượng sàn, "
        },
        {
            "bbox": [
                131.85950191729654,
                770.8659313442116,
                11.98346915132251,
                16.172664948514466
            ],
            "text": "- ",
            "font": {
                "color": [
                    0,
                    0,
                    0,
                    255
                ],
                "name": "/Times New Roman",
                "size": 12
            },
            "text_vi": "- "
        },
        {
            "bbox": [
                193.83608489827176,
                770.8659313442116,
                68.80163451922269,
                16.172664948514466
            ],
            "text": "Druck-, ",
            "font": {
                "color": [
                    0,
                    0,
                    0,
                    255
                ],
                "name": "/Times New Roman",
                "size": 12
            },
            "text_vi": "Áp lực-, "
        },
        {
            "bbox": [
                131.85950191729654,
                787.6668154377331,
                11.98346915132251,
                16.172677123068183
            ],
            "text": "- ",
            "font": {
                "color": [
                    0,
                    0,
                    0,
                    255
                ],
                "name": "/Times New Roman",
                "size": 12
            },
            "text_vi": "- "
        },
        {
            "bbox": [
                193.83608489827176,
                787.6668154377331,
                173.81198055143486,
                16.172677123068183
            ],
            "text": "Temperaturmessung ",
            "font": {
                "color": [
                    0,
                    0,
                    0,
                    255
                ],
                "name": "/Times New Roman",
                "size": 12
            },
            "text_vi": "Đo nhiệt độ "
        },
        {
            "bbox": [
                131.85950191729654,
                804.5042231923276,
                11.98346915132251,
                16.172677123068155
            ],
            "text": "- ",
            "font": {
                "color": [
                    0,
                    0,
                    0,
                    255
                ],
                "name": "/Times New Roman",
                "size": 12
            },
            "text_vi": "- "
        },
        {
            "bbox": [
                193.83608489827176,
                804.5042231923276,
                255.42353221085241,
                16.172677123068155
            ],
            "text": "Schlauchdichtheit-/Verschleiß ",
            "font": {
                "color": [
                    0,
                    0,
                    0,
                    255
                ],
                "name": "/Times New Roman",
                "size": 12
            },
            "text_vi": "Nồi vòi/mặc "
        },
        {
            "bbox": [
                131.85950191729654,
                838.105979204817,
                27.89255634965133,
                16.172677123068155
            ],
            "text": "Zu ",
            "font": {
                "color": [
                    0,
                    0,
                    0,
                    255
                ],
                "name": "/Times New Roman",
                "size": 12
            },
            "text_vi": "ĐẾN "
        },
        {
            "bbox": [
                174.60741786589702,
                838.105979204817,
                92.36916167155206,
                16.172677123068155
            ],
            "text": "Wartungs- ",
            "font": {
                "color": [
                    0,
                    0,
                    0,
                    255
                ],
                "name": "/Times New Roman",
                "size": 12
            },
            "text_vi": "BẢO TRÌ "
        },
        {
            "bbox": [
                281.85261234541736,
                838.105979204817,
                41.79751995905531,
                16.172677123068155
            ],
            "text": "oder ",
            "font": {
                "color": [
                    0,
                    0,
                    0,
                    255
                ],
                "name": "/Times New Roman",
                "size": 12
            },
            "text_vi": "hoặc "
        },
        {
            "bbox": [
                338.65013205250733,
                838.105979204817,
                152.83057594519624,
                16.172677123068155
            ],
            "text": "Reparaturarbeiten ",
            "font": {
                "color": [
                    0,
                    0,
                    0,
                    255
                ],
                "name": "/Times New Roman",
                "size": 12
            },
            "text_vi": "Công việc sửa chữa "
        },
        {
            "bbox": [
                506.3360624313636,
                838.105979204817,
                24.772726856602674,
                16.172677123068155
            ],
            "text": "ist ",
            "font": {
                "color": [
                    0,
                    0,
                    0,
                    255
                ],
                "name": "/Times New Roman",
                "size": 12
            },
            "text_vi": "là "
        },
        {
            "bbox": [
                545.9641437216262,
                838.105979204817,
                30.4132226296241,
                16.172677123068155
            ],
            "text": "die ",
            "font": {
                "color": [
                    0,
                    0,
                    0,
                    255
                ],
                "name": "/Times New Roman",
                "size": 12
            },
            "text_vi": "các "
        },
        {
            "bbox": [
                591.1914156891854,
                838.105979204817,
                80.55784988648361,
                16.172677123068155
            ],
            "text": "jeweilige ",
            "font": {
                "color": [
                    0,
                    0,
                    0,
                    255
                ],
                "name": "/Times New Roman",
                "size": 12
            },
            "text_vi": "tương ứng "
        },
        {
            "bbox": [
                686.6046200093291,
                838.105979204817,
                62.768628422216125,
                16.172677123068155
            ],
            "text": "Pumpe ",
            "font": {
                "color": [
                    0,
                    0,
                    0,
                    255
                ],
                "name": "/Times New Roman",
                "size": 12
            },
            "text_vi": "bơm "
        },
        {
            "bbox": [
                764.2286028652053,
                838.105979204817,
                52.06609761025834,
                16.172677123068155
            ],
            "text": "durch ",
            "font": {
                "color": [
                    0,
                    0,
                    0,
                    255
                ],
                "name": "/Times New Roman",
                "size": 12
            },
            "text_vi": "bởi vì "
        },
        {
            "bbox": [
                831.1500549091236,
                838.105979204817,
                66.92152091444052,
                16.172677123068155
            ],
            "text": "Service ",
            "font": {
                "color": [
                    0,
                    0,
                    0,
                    255
                ],
                "name": "/Times New Roman",
                "size": 12
            },
            "text_vi": "dịch vụ "
        },
        {
            "bbox": [
                131.85950191729654,
                854.9068632983386,
                158.30659169343227,
                16.172689297621844
            ],
            "text": "Handabsperrarmaturen",
            "font": {
                "color": [
                    0,
                    0,
                    0,
                    255
                ],
                "name": "/Times New Roman",
                "size": 12
            },
            "text_vi": "Tắt tay -off phụ kiện"
        },
        {
            "bbox": [
                309.77406504444554,
                854.9068632983386,
                116.7960896358918,
                16.172689297621844
            ],
            "text": "freizuschalten.",
            "font": {
                "color": [
                    0,
                    0,
                    0,
                    255
                ],
                "name": "/Times New Roman",
                "size": 12
            },
            "text_vi": "được mở khóa."
        },
        {
            "bbox": [
                446.1781261140542,
                854.9068632983386,
                21.22458642033547,
                16.172689297621844
            ],
            "text": "Der",
            "font": {
                "color": [
                    0,
                    0,
                    0,
                    255
                ],
                "name": "/Times New Roman",
                "size": 12
            },
            "text_vi": "Các"
        },
        {
            "bbox": [
                487.0106667504759,
                854.9068632983386,
                121.62857922413872,
                16.172689297621844
            ],
            "text": "Anlagenbetrieb",
            "font": {
                "color": [
                    0,
                    0,
                    0,
                    255
                ],
                "name": "/Times New Roman",
                "size": 12
            },
            "text_vi": "Hoạt động thực vật"
        },
        {
            "bbox": [
                628.2472174083314,
                854.9068632983386,
                55.190890946198806,
                16.172689297621844
            ],
            "text": "wird in",
            "font": {
                "color": [
                    0,
                    0,
                    0,
                    255
                ],
                "name": "/Times New Roman",
                "size": 12
            },
            "text_vi": "trở thành trong"
        },
        {
            "bbox": [
                703.0460625706164,
                854.9068632983386,
                41.510536492801634,
                16.172689297621844
            ],
            "text": "dieser",
            "font": {
                "color": [
                    0,
                    0,
                    0,
                    255
                ],
                "name": "/Times New Roman",
                "size": 12
            },
            "text_vi": "cái này"
        },
        {
            "bbox": [
                764.1645532795042,
                854.9068632983386,
                83.17742628876204,
                16.172689297621844
            ],
            "text": "Zeit durch",
            "font": {
                "color": [
                    0,
                    0,
                    0,
                    255
                ],
                "name": "/Times New Roman",
                "size": 12
            },
            "text_vi": "Thời gian qua"
        },
        {
            "bbox": [
                866.949951001983,
                854.9068632983386,
                31.045953335248896,
                16.172689297621844
            ],
            "text": "die ",
            "font": {
                "color": [
                    0,
                    0,
                    0,
                    255
                ],
                "name": "/Times New Roman",
                "size": 12
            },
            "text_vi": "các "
        },
        {
            "bbox": [
                131.85950191729654,
                871.7077595664139,
                109.19591758724857,
                16.172677123068155
            ],
            "text": "zweite Pumpe",
            "font": {
                "color": [
                    0,
                    0,
                    0,
                    255
                ],
                "name": "/Times New Roman",
                "size": 12
            },
            "text_vi": "Máy bơm thứ hai"
        },
        {
            "bbox": [
                261.00571186915084,
                871.7077595664139,
                159.26614746243786,
                16.172677123068155
            ],
            "text": "voll weitergeführt.",
            "font": {
                "color": [
                    0,
                    0,
                    0,
                    255
                ],
                "name": "/Times New Roman",
                "size": 12
            },
            "text_vi": "hoàn toàn tiếp tục."
        },
        {
            "bbox": [
                440.2221344785639,
                871.7077595664139,
                135.86702595466255,
                16.172677123068155
            ],
            "text": "Zur Glättung des",
            "font": {
                "color": [
                    0,
                    0,
                    0,
                    255
                ],
                "name": "/Times New Roman",
                "size": 12
            },
            "text_vi": "Để làm mịn"
        },
        {
            "bbox": [
                596.0394527978322,
                871.7077595664139,
                93.31353149039955,
                16.172677123068155
            ],
            "text": "pulsierenden",
            "font": {
                "color": [
                    0,
                    0,
                    0,
                    255
                ],
                "name": "/Times New Roman",
                "size": 12
            },
            "text_vi": "đập"
        },
        {
            "bbox": [
                709.3032249999458,
                871.7077595664139,
                188.94395343774852,
                16.172677123068155
            ],
            "text": "Pumpenförderstroms ist ",
            "font": {
                "color": [
                    0,
                    0,
                    0,
                    255
                ],
                "name": "/Times New Roman",
                "size": 12
            },
            "text_vi": "Bơm xúc tiến hiện tại là "
        },
        {
            "bbox": [
                131.85950191729654,
                888.5086436599355,
                452.14530920941155,
                16.172683210345
            ],
            "text": "druckseitig ein passiver Pulsationsdämpfer eingesetzt. ",
            "font": {
                "color": [
                    0,
                    0,
                    0,
                    255
                ],
                "name": "/Times New Roman",
                "size": 12
            },
            "text_vi": "Một bộ giảm chấn xung thụ động được chèn vào áp lực."
        }
    ]
}